{"text": " This is New Delhi India and this is my family. Hello. We're here for a week to go to a wedding but before that starts we had a free day. My brother and I told my dad we wanted to go to the town he grew up in. Hussie, how do you spell that? At M S I. Quick stop to stretch and get gas. He hasn't been back in 16 years so he told us he wasn't sure how much he'd remember or if he'd known anyone there. This is going to happen there. As we drove further away from the city things continued to become unfamiliar. We made it to Hussie. There's a certain bond that you can only get from growing up in a place like this. We had tea with my dad's friend brother who became our tour guide for the day. We set off to see our first sight, a school co-founded by my grandfather. He was the first all-girl school here in Hussie. The next stop was a local hangout, an old fort that overlooked the town. He used to sneak away from school and fly kite here. Yeah, we've been run away from school. This was like a getaway place for us. Since this was the place that my dad used to sneak away and fly kites from, it feels like a fitting place to fly the drone. We found a place we can keep in. So, any few, that type, please. This is the house where I grew up. And this is the home I used to study. From the minute we arrived at my dad's old house, people started recognizing me. Even though 40 years had changed a few things about the buildings, the people on the block seemed to be the same. We just pulled up to what used to be my dad's house, everybody is recognizing him, including his neighbors. I am a man. I am a man. I am a man. I remember my name. I am a man. Where is the glass? The glass. I am a man. Wow, I used to think this is a big place. This one. Because we used to sit here. This is my room. Which one? This one. No, this one is one room. Now maybe they made two rooms. It was one room. There were stairs which they removed from there. I used to go up to see that on the corner you see the stairs. I used to go up and I used to like ice there. That's it. You were a man, right? You would have been here when you were young. Yes, I would have been here. I would have been here when I was young. I would have been here. I would have been here when I was young. The rest of the afternoon was spent walking the streets, seeing familiar faces and remembering the stories from growing up here. You know like meeting players. You know like in the evening you get ready and then you come here all the young people come here. I thought the opening is a long dinner. Wait until it's Christmas. This was my grandfather's watch shop. It was the watch shop where my dad learned everything he knows today. More familiar faces and more catching up. As the day went on the uncertainty washed away. This was home. These are our roots and in one way or the other we all felt connected. A man can live in many places and in many houses. But he only has one home.", "segments": [{"id": 0, "seek": 0, "start": 0.0, "end": 7.0, "text": " This is New Delhi India and this is my family.", "tokens": [50364, 639, 307, 1873, 26680, 5282, 293, 341, 307, 452, 1605, 13, 50714, 50714, 2425, 13, 50764, 50764, 492, 434, 510, 337, 257, 1243, 281, 352, 281, 257, 8523, 457, 949, 300, 3719, 321, 632, 257, 1737, 786, 13, 50964, 50964, 1222, 3708, 293, 286, 1907, 452, 3546, 321, 1415, 281, 352, 281, 264, 3954, 415, 6109, 493, 294, 13, 51164, 51164, 389, 2023, 414, 11, 577, 360, 291, 9827, 300, 30, 51264, 51264, 1711, 376, 318, 286, 13, 51614, 51614, 12101, 1590, 281, 5985, 293, 483, 4211, 13, 51764, 51764], "temperature": 0.0, "avg_logprob": -0.2662784327631411, "compression_ratio": 1.4343434343434343, "no_speech_prob": 0.08524263650178909}, {"id": 1, "seek": 0, "start": 7.0, "end": 8.0, "text": " Hello.", "tokens": [50364, 639, 307, 1873, 26680, 5282, 293, 341, 307, 452, 1605, 13, 50714, 50714, 2425, 13, 50764, 50764, 492, 434, 510, 337, 257, 1243, 281, 352, 281, 257, 8523, 457, 949, 300, 3719, 321, 632, 257, 1737, 786, 13, 50964, 50964, 1222, 3708, 293, 286, 1907, 452, 3546, 321, 1415, 281, 352, 281, 264, 3954, 415, 6109, 493, 294, 13, 51164, 51164, 389, 2023, 414, 11, 577, 360, 291, 9827, 300, 30, 51264, 51264, 1711, 376, 318, 286, 13, 51614, 51614, 12101, 1590, 281, 5985, 293, 483, 4211, 13, 51764, 51764], "temperature": 0.0, "avg_logprob": -0.2662784327631411, "compression_ratio": 1.4343434343434343, "no_speech_prob": 0.08524263650178909}, {"id": 2, "seek": 0, "start": 8.0, "end": 12.0, "text": " We're here for a week to go to a wedding but before that starts we had a free day.", "tokens": [50364, 639, 307, 1873, 26680, 5282, 293, 341, 307, 452, 1605, 13, 50714, 50714, 2425, 13, 50764, 50764, 492, 434, 510, 337, 257, 1243, 281, 352, 281, 257, 8523, 457, 949, 300, 3719, 321, 632, 257, 1737, 786, 13, 50964, 50964, 1222, 3708, 293, 286, 1907, 452, 3546, 321, 1415, 281, 352, 281, 264, 3954, 415, 6109, 493, 294, 13, 51164, 51164, 389, 2023, 414, 11, 577, 360, 291, 9827, 300, 30, 51264, 51264, 1711, 376, 318, 286, 13, 51614, 51614, 12101, 1590, 281, 5985, 293, 483, 4211, 13, 51764, 51764], "temperature": 0.0, "avg_logprob": -0.2662784327631411, "compression_ratio": 1.4343434343434343, "no_speech_prob": 0.08524263650178909}, {"id": 3, "seek": 0, "start": 12.0, "end": 16.0, "text": " My brother and I told my dad we wanted to go to the town he grew up in.", "tokens": [50364, 639, 307, 1873, 26680, 5282, 293, 341, 307, 452, 1605, 13, 50714, 50714, 2425, 13, 50764, 50764, 492, 434, 510, 337, 257, 1243, 281, 352, 281, 257, 8523, 457, 949, 300, 3719, 321, 632, 257, 1737, 786, 13, 50964, 50964, 1222, 3708, 293, 286, 1907, 452, 3546, 321, 1415, 281, 352, 281, 264, 3954, 415, 6109, 493, 294, 13, 51164, 51164, 389, 2023, 414, 11, 577, 360, 291, 9827, 300, 30, 51264, 51264, 1711, 376, 318, 286, 13, 51614, 51614, 12101, 1590, 281, 5985, 293, 483, 4211, 13, 51764, 51764], "temperature": 0.0, "avg_logprob": -0.2662784327631411, "compression_ratio": 1.4343434343434343, "no_speech_prob": 0.08524263650178909}, {"id": 4, "seek": 0, "start": 16.0, "end": 18.0, "text": " Hussie, how do you spell that?", "tokens": [50364, 639, 307, 1873, 26680, 5282, 293, 341, 307, 452, 1605, 13, 50714, 50714, 2425, 13, 50764, 50764, 492, 434, 510, 337, 257, 1243, 281, 352, 281, 257, 8523, 457, 949, 300, 3719, 321, 632, 257, 1737, 786, 13, 50964, 50964, 1222, 3708, 293, 286, 1907, 452, 3546, 321, 1415, 281, 352, 281, 264, 3954, 415, 6109, 493, 294, 13, 51164, 51164, 389, 2023, 414, 11, 577, 360, 291, 9827, 300, 30, 51264, 51264, 1711, 376, 318, 286, 13, 51614, 51614, 12101, 1590, 281, 5985, 293, 483, 4211, 13, 51764, 51764], "temperature": 0.0, "avg_logprob": -0.2662784327631411, "compression_ratio": 1.4343434343434343, "no_speech_prob": 0.08524263650178909}, {"id": 5, "seek": 0, "start": 18.0, "end": 25.0, "text": " At M S I.", "tokens": [50364, 639, 307, 1873, 26680, 5282, 293, 341, 307, 452, 1605, 13, 50714, 50714, 2425, 13, 50764, 50764, 492, 434, 510, 337, 257, 1243, 281, 352, 281, 257, 8523, 457, 949, 300, 3719, 321, 632, 257, 1737, 786, 13, 50964, 50964, 1222, 3708, 293, 286, 1907, 452, 3546, 321, 1415, 281, 352, 281, 264, 3954, 415, 6109, 493, 294, 13, 51164, 51164, 389, 2023, 414, 11, 577, 360, 291, 9827, 300, 30, 51264, 51264, 1711, 376, 318, 286, 13, 51614, 51614, 12101, 1590, 281, 5985, 293, 483, 4211, 13, 51764, 51764], "temperature": 0.0, "avg_logprob": -0.2662784327631411, "compression_ratio": 1.4343434343434343, "no_speech_prob": 0.08524263650178909}, {"id": 6, "seek": 0, "start": 25.0, "end": 28.0, "text": " Quick stop to stretch and get gas.", "tokens": [50364, 639, 307, 1873, 26680, 5282, 293, 341, 307, 452, 1605, 13, 50714, 50714, 2425, 13, 50764, 50764, 492, 434, 510, 337, 257, 1243, 281, 352, 281, 257, 8523, 457, 949, 300, 3719, 321, 632, 257, 1737, 786, 13, 50964, 50964, 1222, 3708, 293, 286, 1907, 452, 3546, 321, 1415, 281, 352, 281, 264, 3954, 415, 6109, 493, 294, 13, 51164, 51164, 389, 2023, 414, 11, 577, 360, 291, 9827, 300, 30, 51264, 51264, 1711, 376, 318, 286, 13, 51614, 51614, 12101, 1590, 281, 5985, 293, 483, 4211, 13, 51764, 51764], "temperature": 0.0, "avg_logprob": -0.2662784327631411, "compression_ratio": 1.4343434343434343, "no_speech_prob": 0.08524263650178909}, {"id": 7, "seek": 2800, "start": 28.0, "end": 43.0, "text": " He hasn't been back in 16 years so he told us he wasn't sure how much he'd remember or if he'd known anyone there.", "tokens": [50364, 634, 6132, 380, 668, 646, 294, 3165, 924, 370, 415, 1907, 505, 415, 2067, 380, 988, 577, 709, 415, 1116, 1604, 420, 498, 415, 1116, 2570, 2878, 456, 13, 51114, 51114, 639, 307, 516, 281, 1051, 456, 13, 51264, 51264, 1018, 321, 13226, 3052, 1314, 490, 264, 2307, 721, 7014, 281, 1813, 29415, 13, 51514], "temperature": 0.0, "avg_logprob": -0.21012990516528748, "compression_ratio": 1.3850931677018634, "no_speech_prob": 0.0016304129967465997}, {"id": 8, "seek": 2800, "start": 43.0, "end": 46.0, "text": " This is going to happen there.", "tokens": [50364, 634, 6132, 380, 668, 646, 294, 3165, 924, 370, 415, 1907, 505, 415, 2067, 380, 988, 577, 709, 415, 1116, 1604, 420, 498, 415, 1116, 2570, 2878, 456, 13, 51114, 51114, 639, 307, 516, 281, 1051, 456, 13, 51264, 51264, 1018, 321, 13226, 3052, 1314, 490, 264, 2307, 721, 7014, 281, 1813, 29415, 13, 51514], "temperature": 0.0, "avg_logprob": -0.21012990516528748, "compression_ratio": 1.3850931677018634, "no_speech_prob": 0.0016304129967465997}, {"id": 9, "seek": 4600, "start": 46.0, "end": 60.0, "text": " As we drove further away from the city things continued to become unfamiliar.", "tokens": [50364, 1018, 321, 13226, 3052, 1314, 490, 264, 2307, 721, 7014, 281, 1813, 29415, 13, 51064], "temperature": 0.0, "avg_logprob": -0.1613920436185949, "compression_ratio": 1.0405405405405406, "no_speech_prob": 0.0007566783460788429}, {"id": 10, "seek": 7600, "start": 77.0, "end": 88.0, "text": " We made it to Hussie.", "tokens": [50414, 492, 1027, 309, 281, 389, 2023, 414, 13, 50964, 50964, 821, 311, 257, 1629, 6086, 300, 291, 393, 787, 483, 490, 4194, 493, 294, 257, 1081, 411, 341, 13, 51564, 51564], "temperature": 0.0, "avg_logprob": -0.19611988645611386, "compression_ratio": 1.1063829787234043, "no_speech_prob": 0.15650998055934906}, {"id": 11, "seek": 7600, "start": 88.0, "end": 100.0, "text": " There's a certain bond that you can only get from growing up in a place like this.", "tokens": [50414, 492, 1027, 309, 281, 389, 2023, 414, 13, 50964, 50964, 821, 311, 257, 1629, 6086, 300, 291, 393, 787, 483, 490, 4194, 493, 294, 257, 1081, 411, 341, 13, 51564, 51564], "temperature": 0.0, "avg_logprob": -0.19611988645611386, "compression_ratio": 1.1063829787234043, "no_speech_prob": 0.15650998055934906}, {"id": 12, "seek": 10000, "start": 100.0, "end": 108.0, "text": " We had tea with my dad's friend brother who became our tour guide for the day.", "tokens": [50364, 492, 632, 5817, 365, 452, 3546, 311, 1277, 3708, 567, 3062, 527, 3512, 5934, 337, 264, 786, 13, 50764, 50764, 492, 992, 766, 281, 536, 527, 700, 7860, 11, 257, 1395, 598, 12, 49547, 538, 452, 14754, 13, 51064, 51064, 634, 390, 264, 700, 439, 12, 21322, 1395, 510, 294, 389, 2023, 414, 13, 51514, 51514, 440, 958, 1590, 390, 257, 2654, 3967, 346, 11, 364, 1331, 5009, 300, 32269, 264, 3954, 13, 51714, 51714], "temperature": 0.0, "avg_logprob": -0.09181239388205788, "compression_ratio": 1.4891304347826086, "no_speech_prob": 0.00020305320504121482}, {"id": 13, "seek": 10000, "start": 108.0, "end": 114.0, "text": " We set off to see our first sight, a school co-founded by my grandfather.", "tokens": [50364, 492, 632, 5817, 365, 452, 3546, 311, 1277, 3708, 567, 3062, 527, 3512, 5934, 337, 264, 786, 13, 50764, 50764, 492, 992, 766, 281, 536, 527, 700, 7860, 11, 257, 1395, 598, 12, 49547, 538, 452, 14754, 13, 51064, 51064, 634, 390, 264, 700, 439, 12, 21322, 1395, 510, 294, 389, 2023, 414, 13, 51514, 51514, 440, 958, 1590, 390, 257, 2654, 3967, 346, 11, 364, 1331, 5009, 300, 32269, 264, 3954, 13, 51714, 51714], "temperature": 0.0, "avg_logprob": -0.09181239388205788, "compression_ratio": 1.4891304347826086, "no_speech_prob": 0.00020305320504121482}, {"id": 14, "seek": 10000, "start": 114.0, "end": 123.0, "text": " He was the first all-girl school here in Hussie.", "tokens": [50364, 492, 632, 5817, 365, 452, 3546, 311, 1277, 3708, 567, 3062, 527, 3512, 5934, 337, 264, 786, 13, 50764, 50764, 492, 992, 766, 281, 536, 527, 700, 7860, 11, 257, 1395, 598, 12, 49547, 538, 452, 14754, 13, 51064, 51064, 634, 390, 264, 700, 439, 12, 21322, 1395, 510, 294, 389, 2023, 414, 13, 51514, 51514, 440, 958, 1590, 390, 257, 2654, 3967, 346, 11, 364, 1331, 5009, 300, 32269, 264, 3954, 13, 51714, 51714], "temperature": 0.0, "avg_logprob": -0.09181239388205788, "compression_ratio": 1.4891304347826086, "no_speech_prob": 0.00020305320504121482}, {"id": 15, "seek": 10000, "start": 123.0, "end": 127.0, "text": " The next stop was a local hangout, an old fort that overlooked the town.", "tokens": [50364, 492, 632, 5817, 365, 452, 3546, 311, 1277, 3708, 567, 3062, 527, 3512, 5934, 337, 264, 786, 13, 50764, 50764, 492, 992, 766, 281, 536, 527, 700, 7860, 11, 257, 1395, 598, 12, 49547, 538, 452, 14754, 13, 51064, 51064, 634, 390, 264, 700, 439, 12, 21322, 1395, 510, 294, 389, 2023, 414, 13, 51514, 51514, 440, 958, 1590, 390, 257, 2654, 3967, 346, 11, 364, 1331, 5009, 300, 32269, 264, 3954, 13, 51714, 51714], "temperature": 0.0, "avg_logprob": -0.09181239388205788, "compression_ratio": 1.4891304347826086, "no_speech_prob": 0.00020305320504121482}, {"id": 16, "seek": 12700, "start": 127.0, "end": 130.0, "text": " He used to sneak away from school and fly kite here.", "tokens": [50364, 634, 1143, 281, 13164, 1314, 490, 1395, 293, 3603, 38867, 510, 13, 50514, 50514, 865, 11, 321, 600, 668, 1190, 1314, 490, 1395, 13, 50614, 50614, 639, 390, 411, 257, 483, 10318, 1081, 337, 505, 13, 50864, 50864, 4162, 341, 390, 264, 1081, 300, 452, 3546, 1143, 281, 13164, 1314, 293, 3603, 350, 3324, 490, 11, 51114, 51114, 309, 3417, 411, 257, 15669, 1081, 281, 3603, 264, 13852, 13, 51314, 51314, 467, 311, 257, 707, 1331, 2535, 13, 51514], "temperature": 0.0, "avg_logprob": -0.28442841989022716, "compression_ratio": 1.6927710843373494, "no_speech_prob": 0.0017742181662470102}, {"id": 17, "seek": 12700, "start": 130.0, "end": 132.0, "text": " Yeah, we've been run away from school.", "tokens": [50364, 634, 1143, 281, 13164, 1314, 490, 1395, 293, 3603, 38867, 510, 13, 50514, 50514, 865, 11, 321, 600, 668, 1190, 1314, 490, 1395, 13, 50614, 50614, 639, 390, 411, 257, 483, 10318, 1081, 337, 505, 13, 50864, 50864, 4162, 341, 390, 264, 1081, 300, 452, 3546, 1143, 281, 13164, 1314, 293, 3603, 350, 3324, 490, 11, 51114, 51114, 309, 3417, 411, 257, 15669, 1081, 281, 3603, 264, 13852, 13, 51314, 51314, 467, 311, 257, 707, 1331, 2535, 13, 51514], "temperature": 0.0, "avg_logprob": -0.28442841989022716, "compression_ratio": 1.6927710843373494, "no_speech_prob": 0.0017742181662470102}, {"id": 18, "seek": 12700, "start": 132.0, "end": 137.0, "text": " This was like a getaway place for us.", "tokens": [50364, 634, 1143, 281, 13164, 1314, 490, 1395, 293, 3603, 38867, 510, 13, 50514, 50514, 865, 11, 321, 600, 668, 1190, 1314, 490, 1395, 13, 50614, 50614, 639, 390, 411, 257, 483, 10318, 1081, 337, 505, 13, 50864, 50864, 4162, 341, 390, 264, 1081, 300, 452, 3546, 1143, 281, 13164, 1314, 293, 3603, 350, 3324, 490, 11, 51114, 51114, 309, 3417, 411, 257, 15669, 1081, 281, 3603, 264, 13852, 13, 51314, 51314, 467, 311, 257, 707, 1331, 2535, 13, 51514], "temperature": 0.0, "avg_logprob": -0.28442841989022716, "compression_ratio": 1.6927710843373494, "no_speech_prob": 0.0017742181662470102}, {"id": 19, "seek": 12700, "start": 137.0, "end": 142.0, "text": " Since this was the place that my dad used to sneak away and fly kites from,", "tokens": [50364, 634, 1143, 281, 13164, 1314, 490, 1395, 293, 3603, 38867, 510, 13, 50514, 50514, 865, 11, 321, 600, 668, 1190, 1314, 490, 1395, 13, 50614, 50614, 639, 390, 411, 257, 483, 10318, 1081, 337, 505, 13, 50864, 50864, 4162, 341, 390, 264, 1081, 300, 452, 3546, 1143, 281, 13164, 1314, 293, 3603, 350, 3324, 490, 11, 51114, 51114, 309, 3417, 411, 257, 15669, 1081, 281, 3603, 264, 13852, 13, 51314, 51314, 467, 311, 257, 707, 1331, 2535, 13, 51514], "temperature": 0.0, "avg_logprob": -0.28442841989022716, "compression_ratio": 1.6927710843373494, "no_speech_prob": 0.0017742181662470102}, {"id": 20, "seek": 12700, "start": 142.0, "end": 146.0, "text": " it feels like a fitting place to fly the drone.", "tokens": [50364, 634, 1143, 281, 13164, 1314, 490, 1395, 293, 3603, 38867, 510, 13, 50514, 50514, 865, 11, 321, 600, 668, 1190, 1314, 490, 1395, 13, 50614, 50614, 639, 390, 411, 257, 483, 10318, 1081, 337, 505, 13, 50864, 50864, 4162, 341, 390, 264, 1081, 300, 452, 3546, 1143, 281, 13164, 1314, 293, 3603, 350, 3324, 490, 11, 51114, 51114, 309, 3417, 411, 257, 15669, 1081, 281, 3603, 264, 13852, 13, 51314, 51314, 467, 311, 257, 707, 1331, 2535, 13, 51514], "temperature": 0.0, "avg_logprob": -0.28442841989022716, "compression_ratio": 1.6927710843373494, "no_speech_prob": 0.0017742181662470102}, {"id": 21, "seek": 14600, "start": 146.0, "end": 169.0, "text": " We found a place we can keep in.", "tokens": [50364, 492, 1352, 257, 1081, 321, 393, 1066, 294, 13, 51514, 51514], "temperature": 1.0, "avg_logprob": -2.5234703650841346, "compression_ratio": 0.8, "no_speech_prob": 0.002127893967553973}, {"id": 22, "seek": 16900, "start": 169.0, "end": 179.0, "text": " So, any few, that type, please.", "tokens": [50364, 407, 11, 604, 1326, 11, 300, 2010, 11, 1767, 13, 50864, 50864, 639, 307, 264, 1782, 689, 286, 6109, 493, 13, 51314, 51314, 400, 341, 307, 264, 1280, 286, 1143, 281, 2979, 13, 51464, 51464, 3358, 264, 3456, 321, 6678, 412, 452, 3546, 311, 1331, 1782, 11, 51814, 51814], "temperature": 0.0, "avg_logprob": -0.6425230736825981, "compression_ratio": 1.2833333333333334, "no_speech_prob": 0.15035749971866608}, {"id": 23, "seek": 16900, "start": 179.0, "end": 188.0, "text": " This is the house where I grew up.", "tokens": [50364, 407, 11, 604, 1326, 11, 300, 2010, 11, 1767, 13, 50864, 50864, 639, 307, 264, 1782, 689, 286, 6109, 493, 13, 51314, 51314, 400, 341, 307, 264, 1280, 286, 1143, 281, 2979, 13, 51464, 51464, 3358, 264, 3456, 321, 6678, 412, 452, 3546, 311, 1331, 1782, 11, 51814, 51814], "temperature": 0.0, "avg_logprob": -0.6425230736825981, "compression_ratio": 1.2833333333333334, "no_speech_prob": 0.15035749971866608}, {"id": 24, "seek": 16900, "start": 188.0, "end": 191.0, "text": " And this is the home I used to study.", "tokens": [50364, 407, 11, 604, 1326, 11, 300, 2010, 11, 1767, 13, 50864, 50864, 639, 307, 264, 1782, 689, 286, 6109, 493, 13, 51314, 51314, 400, 341, 307, 264, 1280, 286, 1143, 281, 2979, 13, 51464, 51464, 3358, 264, 3456, 321, 6678, 412, 452, 3546, 311, 1331, 1782, 11, 51814, 51814], "temperature": 0.0, "avg_logprob": -0.6425230736825981, "compression_ratio": 1.2833333333333334, "no_speech_prob": 0.15035749971866608}, {"id": 25, "seek": 16900, "start": 191.0, "end": 198.0, "text": " From the minute we arrived at my dad's old house,", "tokens": [50364, 407, 11, 604, 1326, 11, 300, 2010, 11, 1767, 13, 50864, 50864, 639, 307, 264, 1782, 689, 286, 6109, 493, 13, 51314, 51314, 400, 341, 307, 264, 1280, 286, 1143, 281, 2979, 13, 51464, 51464, 3358, 264, 3456, 321, 6678, 412, 452, 3546, 311, 1331, 1782, 11, 51814, 51814], "temperature": 0.0, "avg_logprob": -0.6425230736825981, "compression_ratio": 1.2833333333333334, "no_speech_prob": 0.15035749971866608}, {"id": 26, "seek": 19800, "start": 198.0, "end": 203.0, "text": " people started recognizing me.", "tokens": [50364, 561, 1409, 18538, 385, 13, 50614, 50614, 2754, 1673, 3356, 924, 632, 3105, 257, 1326, 721, 466, 264, 7446, 11, 50814, 50814, 264, 561, 322, 264, 3461, 6576, 281, 312, 264, 912, 13, 50964, 50964, 492, 445, 7373, 493, 281, 437, 1143, 281, 312, 452, 3546, 311, 1782, 11, 51114, 51114, 2201, 307, 18538, 796, 11, 3009, 702, 12512, 13, 51264, 51264, 286, 669, 257, 587, 13, 51314, 51314, 286, 669, 257, 587, 13, 51364, 51364, 286, 669, 257, 587, 13, 51414, 51414, 286, 1604, 452, 1315, 13, 51464, 51464, 286, 669, 257, 587, 13, 51514, 51514, 2305, 307, 264, 4276, 30, 51564, 51564, 440, 4276, 13, 51614, 51614, 286, 669, 257, 587, 13, 51714], "temperature": 0.0, "avg_logprob": -0.4001929454314403, "compression_ratio": 1.7285714285714286, "no_speech_prob": 0.0013967084232717752}, {"id": 27, "seek": 19800, "start": 203.0, "end": 207.0, "text": " Even though 40 years had changed a few things about the buildings,", "tokens": [50364, 561, 1409, 18538, 385, 13, 50614, 50614, 2754, 1673, 3356, 924, 632, 3105, 257, 1326, 721, 466, 264, 7446, 11, 50814, 50814, 264, 561, 322, 264, 3461, 6576, 281, 312, 264, 912, 13, 50964, 50964, 492, 445, 7373, 493, 281, 437, 1143, 281, 312, 452, 3546, 311, 1782, 11, 51114, 51114, 2201, 307, 18538, 796, 11, 3009, 702, 12512, 13, 51264, 51264, 286, 669, 257, 587, 13, 51314, 51314, 286, 669, 257, 587, 13, 51364, 51364, 286, 669, 257, 587, 13, 51414, 51414, 286, 1604, 452, 1315, 13, 51464, 51464, 286, 669, 257, 587, 13, 51514, 51514, 2305, 307, 264, 4276, 30, 51564, 51564, 440, 4276, 13, 51614, 51614, 286, 669, 257, 587, 13, 51714], "temperature": 0.0, "avg_logprob": -0.4001929454314403, "compression_ratio": 1.7285714285714286, "no_speech_prob": 0.0013967084232717752}, {"id": 28, "seek": 19800, "start": 207.0, "end": 210.0, "text": " the people on the block seemed to be the same.", "tokens": [50364, 561, 1409, 18538, 385, 13, 50614, 50614, 2754, 1673, 3356, 924, 632, 3105, 257, 1326, 721, 466, 264, 7446, 11, 50814, 50814, 264, 561, 322, 264, 3461, 6576, 281, 312, 264, 912, 13, 50964, 50964, 492, 445, 7373, 493, 281, 437, 1143, 281, 312, 452, 3546, 311, 1782, 11, 51114, 51114, 2201, 307, 18538, 796, 11, 3009, 702, 12512, 13, 51264, 51264, 286, 669, 257, 587, 13, 51314, 51314, 286, 669, 257, 587, 13, 51364, 51364, 286, 669, 257, 587, 13, 51414, 51414, 286, 1604, 452, 1315, 13, 51464, 51464, 286, 669, 257, 587, 13, 51514, 51514, 2305, 307, 264, 4276, 30, 51564, 51564, 440, 4276, 13, 51614, 51614, 286, 669, 257, 587, 13, 51714], "temperature": 0.0, "avg_logprob": -0.4001929454314403, "compression_ratio": 1.7285714285714286, "no_speech_prob": 0.0013967084232717752}, {"id": 29, "seek": 19800, "start": 210.0, "end": 213.0, "text": " We just pulled up to what used to be my dad's house,", "tokens": [50364, 561, 1409, 18538, 385, 13, 50614, 50614, 2754, 1673, 3356, 924, 632, 3105, 257, 1326, 721, 466, 264, 7446, 11, 50814, 50814, 264, 561, 322, 264, 3461, 6576, 281, 312, 264, 912, 13, 50964, 50964, 492, 445, 7373, 493, 281, 437, 1143, 281, 312, 452, 3546, 311, 1782, 11, 51114, 51114, 2201, 307, 18538, 796, 11, 3009, 702, 12512, 13, 51264, 51264, 286, 669, 257, 587, 13, 51314, 51314, 286, 669, 257, 587, 13, 51364, 51364, 286, 669, 257, 587, 13, 51414, 51414, 286, 1604, 452, 1315, 13, 51464, 51464, 286, 669, 257, 587, 13, 51514, 51514, 2305, 307, 264, 4276, 30, 51564, 51564, 440, 4276, 13, 51614, 51614, 286, 669, 257, 587, 13, 51714], "temperature": 0.0, "avg_logprob": -0.4001929454314403, "compression_ratio": 1.7285714285714286, "no_speech_prob": 0.0013967084232717752}, {"id": 30, "seek": 19800, "start": 213.0, "end": 216.0, "text": " everybody is recognizing him, including his neighbors.", "tokens": [50364, 561, 1409, 18538, 385, 13, 50614, 50614, 2754, 1673, 3356, 924, 632, 3105, 257, 1326, 721, 466, 264, 7446, 11, 50814, 50814, 264, 561, 322, 264, 3461, 6576, 281, 312, 264, 912, 13, 50964, 50964, 492, 445, 7373, 493, 281, 437, 1143, 281, 312, 452, 3546, 311, 1782, 11, 51114, 51114, 2201, 307, 18538, 796, 11, 3009, 702, 12512, 13, 51264, 51264, 286, 669, 257, 587, 13, 51314, 51314, 286, 669, 257, 587, 13, 51364, 51364, 286, 669, 257, 587, 13, 51414, 51414, 286, 1604, 452, 1315, 13, 51464, 51464, 286, 669, 257, 587, 13, 51514, 51514, 2305, 307, 264, 4276, 30, 51564, 51564, 440, 4276, 13, 51614, 51614, 286, 669, 257, 587, 13, 51714], "temperature": 0.0, "avg_logprob": -0.4001929454314403, "compression_ratio": 1.7285714285714286, "no_speech_prob": 0.0013967084232717752}, {"id": 31, "seek": 19800, "start": 216.0, "end": 217.0, "text": " I am a man.", "tokens": [50364, 561, 1409, 18538, 385, 13, 50614, 50614, 2754, 1673, 3356, 924, 632, 3105, 257, 1326, 721, 466, 264, 7446, 11, 50814, 50814, 264, 561, 322, 264, 3461, 6576, 281, 312, 264, 912, 13, 50964, 50964, 492, 445, 7373, 493, 281, 437, 1143, 281, 312, 452, 3546, 311, 1782, 11, 51114, 51114, 2201, 307, 18538, 796, 11, 3009, 702, 12512, 13, 51264, 51264, 286, 669, 257, 587, 13, 51314, 51314, 286, 669, 257, 587, 13, 51364, 51364, 286, 669, 257, 587, 13, 51414, 51414, 286, 1604, 452, 1315, 13, 51464, 51464, 286, 669, 257, 587, 13, 51514, 51514, 2305, 307, 264, 4276, 30, 51564, 51564, 440, 4276, 13, 51614, 51614, 286, 669, 257, 587, 13, 51714], "temperature": 0.0, "avg_logprob": -0.4001929454314403, "compression_ratio": 1.7285714285714286, "no_speech_prob": 0.0013967084232717752}, {"id": 32, "seek": 19800, "start": 217.0, "end": 218.0, "text": " I am a man.", "tokens": [50364, 561, 1409, 18538, 385, 13, 50614, 50614, 2754, 1673, 3356, 924, 632, 3105, 257, 1326, 721, 466, 264, 7446, 11, 50814, 50814, 264, 561, 322, 264, 3461, 6576, 281, 312, 264, 912, 13, 50964, 50964, 492, 445, 7373, 493, 281, 437, 1143, 281, 312, 452, 3546, 311, 1782, 11, 51114, 51114, 2201, 307, 18538, 796, 11, 3009, 702, 12512, 13, 51264, 51264, 286, 669, 257, 587, 13, 51314, 51314, 286, 669, 257, 587, 13, 51364, 51364, 286, 669, 257, 587, 13, 51414, 51414, 286, 1604, 452, 1315, 13, 51464, 51464, 286, 669, 257, 587, 13, 51514, 51514, 2305, 307, 264, 4276, 30, 51564, 51564, 440, 4276, 13, 51614, 51614, 286, 669, 257, 587, 13, 51714], "temperature": 0.0, "avg_logprob": -0.4001929454314403, "compression_ratio": 1.7285714285714286, "no_speech_prob": 0.0013967084232717752}, {"id": 33, "seek": 19800, "start": 218.0, "end": 219.0, "text": " I am a man.", "tokens": [50364, 561, 1409, 18538, 385, 13, 50614, 50614, 2754, 1673, 3356, 924, 632, 3105, 257, 1326, 721, 466, 264, 7446, 11, 50814, 50814, 264, 561, 322, 264, 3461, 6576, 281, 312, 264, 912, 13, 50964, 50964, 492, 445, 7373, 493, 281, 437, 1143, 281, 312, 452, 3546, 311, 1782, 11, 51114, 51114, 2201, 307, 18538, 796, 11, 3009, 702, 12512, 13, 51264, 51264, 286, 669, 257, 587, 13, 51314, 51314, 286, 669, 257, 587, 13, 51364, 51364, 286, 669, 257, 587, 13, 51414, 51414, 286, 1604, 452, 1315, 13, 51464, 51464, 286, 669, 257, 587, 13, 51514, 51514, 2305, 307, 264, 4276, 30, 51564, 51564, 440, 4276, 13, 51614, 51614, 286, 669, 257, 587, 13, 51714], "temperature": 0.0, "avg_logprob": -0.4001929454314403, "compression_ratio": 1.7285714285714286, "no_speech_prob": 0.0013967084232717752}, {"id": 34, "seek": 19800, "start": 219.0, "end": 220.0, "text": " I remember my name.", "tokens": [50364, 561, 1409, 18538, 385, 13, 50614, 50614, 2754, 1673, 3356, 924, 632, 3105, 257, 1326, 721, 466, 264, 7446, 11, 50814, 50814, 264, 561, 322, 264, 3461, 6576, 281, 312, 264, 912, 13, 50964, 50964, 492, 445, 7373, 493, 281, 437, 1143, 281, 312, 452, 3546, 311, 1782, 11, 51114, 51114, 2201, 307, 18538, 796, 11, 3009, 702, 12512, 13, 51264, 51264, 286, 669, 257, 587, 13, 51314, 51314, 286, 669, 257, 587, 13, 51364, 51364, 286, 669, 257, 587, 13, 51414, 51414, 286, 1604, 452, 1315, 13, 51464, 51464, 286, 669, 257, 587, 13, 51514, 51514, 2305, 307, 264, 4276, 30, 51564, 51564, 440, 4276, 13, 51614, 51614, 286, 669, 257, 587, 13, 51714], "temperature": 0.0, "avg_logprob": -0.4001929454314403, "compression_ratio": 1.7285714285714286, "no_speech_prob": 0.0013967084232717752}, {"id": 35, "seek": 19800, "start": 220.0, "end": 221.0, "text": " I am a man.", "tokens": [50364, 561, 1409, 18538, 385, 13, 50614, 50614, 2754, 1673, 3356, 924, 632, 3105, 257, 1326, 721, 466, 264, 7446, 11, 50814, 50814, 264, 561, 322, 264, 3461, 6576, 281, 312, 264, 912, 13, 50964, 50964, 492, 445, 7373, 493, 281, 437, 1143, 281, 312, 452, 3546, 311, 1782, 11, 51114, 51114, 2201, 307, 18538, 796, 11, 3009, 702, 12512, 13, 51264, 51264, 286, 669, 257, 587, 13, 51314, 51314, 286, 669, 257, 587, 13, 51364, 51364, 286, 669, 257, 587, 13, 51414, 51414, 286, 1604, 452, 1315, 13, 51464, 51464, 286, 669, 257, 587, 13, 51514, 51514, 2305, 307, 264, 4276, 30, 51564, 51564, 440, 4276, 13, 51614, 51614, 286, 669, 257, 587, 13, 51714], "temperature": 0.0, "avg_logprob": -0.4001929454314403, "compression_ratio": 1.7285714285714286, "no_speech_prob": 0.0013967084232717752}, {"id": 36, "seek": 19800, "start": 221.0, "end": 222.0, "text": " Where is the glass?", "tokens": [50364, 561, 1409, 18538, 385, 13, 50614, 50614, 2754, 1673, 3356, 924, 632, 3105, 257, 1326, 721, 466, 264, 7446, 11, 50814, 50814, 264, 561, 322, 264, 3461, 6576, 281, 312, 264, 912, 13, 50964, 50964, 492, 445, 7373, 493, 281, 437, 1143, 281, 312, 452, 3546, 311, 1782, 11, 51114, 51114, 2201, 307, 18538, 796, 11, 3009, 702, 12512, 13, 51264, 51264, 286, 669, 257, 587, 13, 51314, 51314, 286, 669, 257, 587, 13, 51364, 51364, 286, 669, 257, 587, 13, 51414, 51414, 286, 1604, 452, 1315, 13, 51464, 51464, 286, 669, 257, 587, 13, 51514, 51514, 2305, 307, 264, 4276, 30, 51564, 51564, 440, 4276, 13, 51614, 51614, 286, 669, 257, 587, 13, 51714], "temperature": 0.0, "avg_logprob": -0.4001929454314403, "compression_ratio": 1.7285714285714286, "no_speech_prob": 0.0013967084232717752}, {"id": 37, "seek": 19800, "start": 222.0, "end": 223.0, "text": " The glass.", "tokens": [50364, 561, 1409, 18538, 385, 13, 50614, 50614, 2754, 1673, 3356, 924, 632, 3105, 257, 1326, 721, 466, 264, 7446, 11, 50814, 50814, 264, 561, 322, 264, 3461, 6576, 281, 312, 264, 912, 13, 50964, 50964, 492, 445, 7373, 493, 281, 437, 1143, 281, 312, 452, 3546, 311, 1782, 11, 51114, 51114, 2201, 307, 18538, 796, 11, 3009, 702, 12512, 13, 51264, 51264, 286, 669, 257, 587, 13, 51314, 51314, 286, 669, 257, 587, 13, 51364, 51364, 286, 669, 257, 587, 13, 51414, 51414, 286, 1604, 452, 1315, 13, 51464, 51464, 286, 669, 257, 587, 13, 51514, 51514, 2305, 307, 264, 4276, 30, 51564, 51564, 440, 4276, 13, 51614, 51614, 286, 669, 257, 587, 13, 51714], "temperature": 0.0, "avg_logprob": -0.4001929454314403, "compression_ratio": 1.7285714285714286, "no_speech_prob": 0.0013967084232717752}, {"id": 38, "seek": 22300, "start": 223.0, "end": 230.0, "text": " I am a man.", "tokens": [50364, 286, 669, 257, 587, 13, 50714, 50714, 3153, 11, 286, 1143, 281, 519, 341, 307, 257, 955, 1081, 13, 50914, 50914, 639, 472, 13, 50964, 50964, 1436, 321, 1143, 281, 1394, 510, 13, 51114, 51114, 639, 307, 452, 1808, 13, 51214, 51214, 3013, 472, 30, 51264, 51264, 639, 472, 13, 51314, 51314, 883, 11, 341, 472, 307, 472, 1808, 13, 51414, 51414, 823, 1310, 436, 1027, 732, 9396, 13, 51514, 51514, 467, 390, 472, 1808, 13, 51564, 51564, 821, 645, 13471, 597, 436, 7261, 490, 456, 13, 51664, 51664, 286, 1143, 281, 352, 493, 281, 536, 300, 322, 264, 4538, 291, 536, 264, 13471, 13, 51814, 51814], "temperature": 0.0, "avg_logprob": -0.25107126498441085, "compression_ratio": 1.7119565217391304, "no_speech_prob": 0.008059035986661911}, {"id": 39, "seek": 22300, "start": 230.0, "end": 234.0, "text": " Wow, I used to think this is a big place.", "tokens": [50364, 286, 669, 257, 587, 13, 50714, 50714, 3153, 11, 286, 1143, 281, 519, 341, 307, 257, 955, 1081, 13, 50914, 50914, 639, 472, 13, 50964, 50964, 1436, 321, 1143, 281, 1394, 510, 13, 51114, 51114, 639, 307, 452, 1808, 13, 51214, 51214, 3013, 472, 30, 51264, 51264, 639, 472, 13, 51314, 51314, 883, 11, 341, 472, 307, 472, 1808, 13, 51414, 51414, 823, 1310, 436, 1027, 732, 9396, 13, 51514, 51514, 467, 390, 472, 1808, 13, 51564, 51564, 821, 645, 13471, 597, 436, 7261, 490, 456, 13, 51664, 51664, 286, 1143, 281, 352, 493, 281, 536, 300, 322, 264, 4538, 291, 536, 264, 13471, 13, 51814, 51814], "temperature": 0.0, "avg_logprob": -0.25107126498441085, "compression_ratio": 1.7119565217391304, "no_speech_prob": 0.008059035986661911}, {"id": 40, "seek": 22300, "start": 234.0, "end": 235.0, "text": " This one.", "tokens": [50364, 286, 669, 257, 587, 13, 50714, 50714, 3153, 11, 286, 1143, 281, 519, 341, 307, 257, 955, 1081, 13, 50914, 50914, 639, 472, 13, 50964, 50964, 1436, 321, 1143, 281, 1394, 510, 13, 51114, 51114, 639, 307, 452, 1808, 13, 51214, 51214, 3013, 472, 30, 51264, 51264, 639, 472, 13, 51314, 51314, 883, 11, 341, 472, 307, 472, 1808, 13, 51414, 51414, 823, 1310, 436, 1027, 732, 9396, 13, 51514, 51514, 467, 390, 472, 1808, 13, 51564, 51564, 821, 645, 13471, 597, 436, 7261, 490, 456, 13, 51664, 51664, 286, 1143, 281, 352, 493, 281, 536, 300, 322, 264, 4538, 291, 536, 264, 13471, 13, 51814, 51814], "temperature": 0.0, "avg_logprob": -0.25107126498441085, "compression_ratio": 1.7119565217391304, "no_speech_prob": 0.008059035986661911}, {"id": 41, "seek": 22300, "start": 235.0, "end": 238.0, "text": " Because we used to sit here.", "tokens": [50364, 286, 669, 257, 587, 13, 50714, 50714, 3153, 11, 286, 1143, 281, 519, 341, 307, 257, 955, 1081, 13, 50914, 50914, 639, 472, 13, 50964, 50964, 1436, 321, 1143, 281, 1394, 510, 13, 51114, 51114, 639, 307, 452, 1808, 13, 51214, 51214, 3013, 472, 30, 51264, 51264, 639, 472, 13, 51314, 51314, 883, 11, 341, 472, 307, 472, 1808, 13, 51414, 51414, 823, 1310, 436, 1027, 732, 9396, 13, 51514, 51514, 467, 390, 472, 1808, 13, 51564, 51564, 821, 645, 13471, 597, 436, 7261, 490, 456, 13, 51664, 51664, 286, 1143, 281, 352, 493, 281, 536, 300, 322, 264, 4538, 291, 536, 264, 13471, 13, 51814, 51814], "temperature": 0.0, "avg_logprob": -0.25107126498441085, "compression_ratio": 1.7119565217391304, "no_speech_prob": 0.008059035986661911}, {"id": 42, "seek": 22300, "start": 238.0, "end": 240.0, "text": " This is my room.", "tokens": [50364, 286, 669, 257, 587, 13, 50714, 50714, 3153, 11, 286, 1143, 281, 519, 341, 307, 257, 955, 1081, 13, 50914, 50914, 639, 472, 13, 50964, 50964, 1436, 321, 1143, 281, 1394, 510, 13, 51114, 51114, 639, 307, 452, 1808, 13, 51214, 51214, 3013, 472, 30, 51264, 51264, 639, 472, 13, 51314, 51314, 883, 11, 341, 472, 307, 472, 1808, 13, 51414, 51414, 823, 1310, 436, 1027, 732, 9396, 13, 51514, 51514, 467, 390, 472, 1808, 13, 51564, 51564, 821, 645, 13471, 597, 436, 7261, 490, 456, 13, 51664, 51664, 286, 1143, 281, 352, 493, 281, 536, 300, 322, 264, 4538, 291, 536, 264, 13471, 13, 51814, 51814], "temperature": 0.0, "avg_logprob": -0.25107126498441085, "compression_ratio": 1.7119565217391304, "no_speech_prob": 0.008059035986661911}, {"id": 43, "seek": 22300, "start": 240.0, "end": 241.0, "text": " Which one?", "tokens": [50364, 286, 669, 257, 587, 13, 50714, 50714, 3153, 11, 286, 1143, 281, 519, 341, 307, 257, 955, 1081, 13, 50914, 50914, 639, 472, 13, 50964, 50964, 1436, 321, 1143, 281, 1394, 510, 13, 51114, 51114, 639, 307, 452, 1808, 13, 51214, 51214, 3013, 472, 30, 51264, 51264, 639, 472, 13, 51314, 51314, 883, 11, 341, 472, 307, 472, 1808, 13, 51414, 51414, 823, 1310, 436, 1027, 732, 9396, 13, 51514, 51514, 467, 390, 472, 1808, 13, 51564, 51564, 821, 645, 13471, 597, 436, 7261, 490, 456, 13, 51664, 51664, 286, 1143, 281, 352, 493, 281, 536, 300, 322, 264, 4538, 291, 536, 264, 13471, 13, 51814, 51814], "temperature": 0.0, "avg_logprob": -0.25107126498441085, "compression_ratio": 1.7119565217391304, "no_speech_prob": 0.008059035986661911}, {"id": 44, "seek": 22300, "start": 241.0, "end": 242.0, "text": " This one.", "tokens": [50364, 286, 669, 257, 587, 13, 50714, 50714, 3153, 11, 286, 1143, 281, 519, 341, 307, 257, 955, 1081, 13, 50914, 50914, 639, 472, 13, 50964, 50964, 1436, 321, 1143, 281, 1394, 510, 13, 51114, 51114, 639, 307, 452, 1808, 13, 51214, 51214, 3013, 472, 30, 51264, 51264, 639, 472, 13, 51314, 51314, 883, 11, 341, 472, 307, 472, 1808, 13, 51414, 51414, 823, 1310, 436, 1027, 732, 9396, 13, 51514, 51514, 467, 390, 472, 1808, 13, 51564, 51564, 821, 645, 13471, 597, 436, 7261, 490, 456, 13, 51664, 51664, 286, 1143, 281, 352, 493, 281, 536, 300, 322, 264, 4538, 291, 536, 264, 13471, 13, 51814, 51814], "temperature": 0.0, "avg_logprob": -0.25107126498441085, "compression_ratio": 1.7119565217391304, "no_speech_prob": 0.008059035986661911}, {"id": 45, "seek": 22300, "start": 242.0, "end": 244.0, "text": " No, this one is one room.", "tokens": [50364, 286, 669, 257, 587, 13, 50714, 50714, 3153, 11, 286, 1143, 281, 519, 341, 307, 257, 955, 1081, 13, 50914, 50914, 639, 472, 13, 50964, 50964, 1436, 321, 1143, 281, 1394, 510, 13, 51114, 51114, 639, 307, 452, 1808, 13, 51214, 51214, 3013, 472, 30, 51264, 51264, 639, 472, 13, 51314, 51314, 883, 11, 341, 472, 307, 472, 1808, 13, 51414, 51414, 823, 1310, 436, 1027, 732, 9396, 13, 51514, 51514, 467, 390, 472, 1808, 13, 51564, 51564, 821, 645, 13471, 597, 436, 7261, 490, 456, 13, 51664, 51664, 286, 1143, 281, 352, 493, 281, 536, 300, 322, 264, 4538, 291, 536, 264, 13471, 13, 51814, 51814], "temperature": 0.0, "avg_logprob": -0.25107126498441085, "compression_ratio": 1.7119565217391304, "no_speech_prob": 0.008059035986661911}, {"id": 46, "seek": 22300, "start": 244.0, "end": 246.0, "text": " Now maybe they made two rooms.", "tokens": [50364, 286, 669, 257, 587, 13, 50714, 50714, 3153, 11, 286, 1143, 281, 519, 341, 307, 257, 955, 1081, 13, 50914, 50914, 639, 472, 13, 50964, 50964, 1436, 321, 1143, 281, 1394, 510, 13, 51114, 51114, 639, 307, 452, 1808, 13, 51214, 51214, 3013, 472, 30, 51264, 51264, 639, 472, 13, 51314, 51314, 883, 11, 341, 472, 307, 472, 1808, 13, 51414, 51414, 823, 1310, 436, 1027, 732, 9396, 13, 51514, 51514, 467, 390, 472, 1808, 13, 51564, 51564, 821, 645, 13471, 597, 436, 7261, 490, 456, 13, 51664, 51664, 286, 1143, 281, 352, 493, 281, 536, 300, 322, 264, 4538, 291, 536, 264, 13471, 13, 51814, 51814], "temperature": 0.0, "avg_logprob": -0.25107126498441085, "compression_ratio": 1.7119565217391304, "no_speech_prob": 0.008059035986661911}, {"id": 47, "seek": 22300, "start": 246.0, "end": 247.0, "text": " It was one room.", "tokens": [50364, 286, 669, 257, 587, 13, 50714, 50714, 3153, 11, 286, 1143, 281, 519, 341, 307, 257, 955, 1081, 13, 50914, 50914, 639, 472, 13, 50964, 50964, 1436, 321, 1143, 281, 1394, 510, 13, 51114, 51114, 639, 307, 452, 1808, 13, 51214, 51214, 3013, 472, 30, 51264, 51264, 639, 472, 13, 51314, 51314, 883, 11, 341, 472, 307, 472, 1808, 13, 51414, 51414, 823, 1310, 436, 1027, 732, 9396, 13, 51514, 51514, 467, 390, 472, 1808, 13, 51564, 51564, 821, 645, 13471, 597, 436, 7261, 490, 456, 13, 51664, 51664, 286, 1143, 281, 352, 493, 281, 536, 300, 322, 264, 4538, 291, 536, 264, 13471, 13, 51814, 51814], "temperature": 0.0, "avg_logprob": -0.25107126498441085, "compression_ratio": 1.7119565217391304, "no_speech_prob": 0.008059035986661911}, {"id": 48, "seek": 22300, "start": 247.0, "end": 249.0, "text": " There were stairs which they removed from there.", "tokens": [50364, 286, 669, 257, 587, 13, 50714, 50714, 3153, 11, 286, 1143, 281, 519, 341, 307, 257, 955, 1081, 13, 50914, 50914, 639, 472, 13, 50964, 50964, 1436, 321, 1143, 281, 1394, 510, 13, 51114, 51114, 639, 307, 452, 1808, 13, 51214, 51214, 3013, 472, 30, 51264, 51264, 639, 472, 13, 51314, 51314, 883, 11, 341, 472, 307, 472, 1808, 13, 51414, 51414, 823, 1310, 436, 1027, 732, 9396, 13, 51514, 51514, 467, 390, 472, 1808, 13, 51564, 51564, 821, 645, 13471, 597, 436, 7261, 490, 456, 13, 51664, 51664, 286, 1143, 281, 352, 493, 281, 536, 300, 322, 264, 4538, 291, 536, 264, 13471, 13, 51814, 51814], "temperature": 0.0, "avg_logprob": -0.25107126498441085, "compression_ratio": 1.7119565217391304, "no_speech_prob": 0.008059035986661911}, {"id": 49, "seek": 22300, "start": 249.0, "end": 252.0, "text": " I used to go up to see that on the corner you see the stairs.", "tokens": [50364, 286, 669, 257, 587, 13, 50714, 50714, 3153, 11, 286, 1143, 281, 519, 341, 307, 257, 955, 1081, 13, 50914, 50914, 639, 472, 13, 50964, 50964, 1436, 321, 1143, 281, 1394, 510, 13, 51114, 51114, 639, 307, 452, 1808, 13, 51214, 51214, 3013, 472, 30, 51264, 51264, 639, 472, 13, 51314, 51314, 883, 11, 341, 472, 307, 472, 1808, 13, 51414, 51414, 823, 1310, 436, 1027, 732, 9396, 13, 51514, 51514, 467, 390, 472, 1808, 13, 51564, 51564, 821, 645, 13471, 597, 436, 7261, 490, 456, 13, 51664, 51664, 286, 1143, 281, 352, 493, 281, 536, 300, 322, 264, 4538, 291, 536, 264, 13471, 13, 51814, 51814], "temperature": 0.0, "avg_logprob": -0.25107126498441085, "compression_ratio": 1.7119565217391304, "no_speech_prob": 0.008059035986661911}, {"id": 50, "seek": 25200, "start": 252.0, "end": 257.0, "text": " I used to go up and I used to like ice there.", "tokens": [50364, 286, 1143, 281, 352, 493, 293, 286, 1143, 281, 411, 4435, 456, 13, 50614, 50614, 663, 311, 309, 13, 50664, 50664, 509, 645, 257, 587, 11, 558, 30, 50714, 50714, 509, 576, 362, 668, 510, 562, 291, 645, 2037, 13, 50814, 50814, 1079, 11, 286, 576, 362, 668, 510, 13, 50914, 50914, 286, 576, 362, 668, 510, 562, 286, 390, 2037, 13, 51014, 51014, 286, 576, 362, 668, 510, 13, 51064, 51064, 286, 576, 362, 668, 510, 562, 286, 390, 2037, 13, 51164, 51164, 440, 1472, 295, 264, 6499, 390, 4418, 4494, 264, 8481, 11, 51464, 51464, 2577, 4963, 8475, 293, 20719, 264, 3676, 490, 4194, 493, 510, 13, 51714, 51714, 509, 458, 411, 3440, 4150, 13, 51814, 51814], "temperature": 0.2, "avg_logprob": -0.5015249961663869, "compression_ratio": 2.0588235294117645, "no_speech_prob": 0.0032136384397745132}, {"id": 51, "seek": 25200, "start": 257.0, "end": 258.0, "text": " That's it.", "tokens": [50364, 286, 1143, 281, 352, 493, 293, 286, 1143, 281, 411, 4435, 456, 13, 50614, 50614, 663, 311, 309, 13, 50664, 50664, 509, 645, 257, 587, 11, 558, 30, 50714, 50714, 509, 576, 362, 668, 510, 562, 291, 645, 2037, 13, 50814, 50814, 1079, 11, 286, 576, 362, 668, 510, 13, 50914, 50914, 286, 576, 362, 668, 510, 562, 286, 390, 2037, 13, 51014, 51014, 286, 576, 362, 668, 510, 13, 51064, 51064, 286, 576, 362, 668, 510, 562, 286, 390, 2037, 13, 51164, 51164, 440, 1472, 295, 264, 6499, 390, 4418, 4494, 264, 8481, 11, 51464, 51464, 2577, 4963, 8475, 293, 20719, 264, 3676, 490, 4194, 493, 510, 13, 51714, 51714, 509, 458, 411, 3440, 4150, 13, 51814, 51814], "temperature": 0.2, "avg_logprob": -0.5015249961663869, "compression_ratio": 2.0588235294117645, "no_speech_prob": 0.0032136384397745132}, {"id": 52, "seek": 25200, "start": 258.0, "end": 259.0, "text": " You were a man, right?", "tokens": [50364, 286, 1143, 281, 352, 493, 293, 286, 1143, 281, 411, 4435, 456, 13, 50614, 50614, 663, 311, 309, 13, 50664, 50664, 509, 645, 257, 587, 11, 558, 30, 50714, 50714, 509, 576, 362, 668, 510, 562, 291, 645, 2037, 13, 50814, 50814, 1079, 11, 286, 576, 362, 668, 510, 13, 50914, 50914, 286, 576, 362, 668, 510, 562, 286, 390, 2037, 13, 51014, 51014, 286, 576, 362, 668, 510, 13, 51064, 51064, 286, 576, 362, 668, 510, 562, 286, 390, 2037, 13, 51164, 51164, 440, 1472, 295, 264, 6499, 390, 4418, 4494, 264, 8481, 11, 51464, 51464, 2577, 4963, 8475, 293, 20719, 264, 3676, 490, 4194, 493, 510, 13, 51714, 51714, 509, 458, 411, 3440, 4150, 13, 51814, 51814], "temperature": 0.2, "avg_logprob": -0.5015249961663869, "compression_ratio": 2.0588235294117645, "no_speech_prob": 0.0032136384397745132}, {"id": 53, "seek": 25200, "start": 259.0, "end": 261.0, "text": " You would have been here when you were young.", "tokens": [50364, 286, 1143, 281, 352, 493, 293, 286, 1143, 281, 411, 4435, 456, 13, 50614, 50614, 663, 311, 309, 13, 50664, 50664, 509, 645, 257, 587, 11, 558, 30, 50714, 50714, 509, 576, 362, 668, 510, 562, 291, 645, 2037, 13, 50814, 50814, 1079, 11, 286, 576, 362, 668, 510, 13, 50914, 50914, 286, 576, 362, 668, 510, 562, 286, 390, 2037, 13, 51014, 51014, 286, 576, 362, 668, 510, 13, 51064, 51064, 286, 576, 362, 668, 510, 562, 286, 390, 2037, 13, 51164, 51164, 440, 1472, 295, 264, 6499, 390, 4418, 4494, 264, 8481, 11, 51464, 51464, 2577, 4963, 8475, 293, 20719, 264, 3676, 490, 4194, 493, 510, 13, 51714, 51714, 509, 458, 411, 3440, 4150, 13, 51814, 51814], "temperature": 0.2, "avg_logprob": -0.5015249961663869, "compression_ratio": 2.0588235294117645, "no_speech_prob": 0.0032136384397745132}, {"id": 54, "seek": 25200, "start": 261.0, "end": 263.0, "text": " Yes, I would have been here.", "tokens": [50364, 286, 1143, 281, 352, 493, 293, 286, 1143, 281, 411, 4435, 456, 13, 50614, 50614, 663, 311, 309, 13, 50664, 50664, 509, 645, 257, 587, 11, 558, 30, 50714, 50714, 509, 576, 362, 668, 510, 562, 291, 645, 2037, 13, 50814, 50814, 1079, 11, 286, 576, 362, 668, 510, 13, 50914, 50914, 286, 576, 362, 668, 510, 562, 286, 390, 2037, 13, 51014, 51014, 286, 576, 362, 668, 510, 13, 51064, 51064, 286, 576, 362, 668, 510, 562, 286, 390, 2037, 13, 51164, 51164, 440, 1472, 295, 264, 6499, 390, 4418, 4494, 264, 8481, 11, 51464, 51464, 2577, 4963, 8475, 293, 20719, 264, 3676, 490, 4194, 493, 510, 13, 51714, 51714, 509, 458, 411, 3440, 4150, 13, 51814, 51814], "temperature": 0.2, "avg_logprob": -0.5015249961663869, "compression_ratio": 2.0588235294117645, "no_speech_prob": 0.0032136384397745132}, {"id": 55, "seek": 25200, "start": 263.0, "end": 265.0, "text": " I would have been here when I was young.", "tokens": [50364, 286, 1143, 281, 352, 493, 293, 286, 1143, 281, 411, 4435, 456, 13, 50614, 50614, 663, 311, 309, 13, 50664, 50664, 509, 645, 257, 587, 11, 558, 30, 50714, 50714, 509, 576, 362, 668, 510, 562, 291, 645, 2037, 13, 50814, 50814, 1079, 11, 286, 576, 362, 668, 510, 13, 50914, 50914, 286, 576, 362, 668, 510, 562, 286, 390, 2037, 13, 51014, 51014, 286, 576, 362, 668, 510, 13, 51064, 51064, 286, 576, 362, 668, 510, 562, 286, 390, 2037, 13, 51164, 51164, 440, 1472, 295, 264, 6499, 390, 4418, 4494, 264, 8481, 11, 51464, 51464, 2577, 4963, 8475, 293, 20719, 264, 3676, 490, 4194, 493, 510, 13, 51714, 51714, 509, 458, 411, 3440, 4150, 13, 51814, 51814], "temperature": 0.2, "avg_logprob": -0.5015249961663869, "compression_ratio": 2.0588235294117645, "no_speech_prob": 0.0032136384397745132}, {"id": 56, "seek": 25200, "start": 265.0, "end": 266.0, "text": " I would have been here.", "tokens": [50364, 286, 1143, 281, 352, 493, 293, 286, 1143, 281, 411, 4435, 456, 13, 50614, 50614, 663, 311, 309, 13, 50664, 50664, 509, 645, 257, 587, 11, 558, 30, 50714, 50714, 509, 576, 362, 668, 510, 562, 291, 645, 2037, 13, 50814, 50814, 1079, 11, 286, 576, 362, 668, 510, 13, 50914, 50914, 286, 576, 362, 668, 510, 562, 286, 390, 2037, 13, 51014, 51014, 286, 576, 362, 668, 510, 13, 51064, 51064, 286, 576, 362, 668, 510, 562, 286, 390, 2037, 13, 51164, 51164, 440, 1472, 295, 264, 6499, 390, 4418, 4494, 264, 8481, 11, 51464, 51464, 2577, 4963, 8475, 293, 20719, 264, 3676, 490, 4194, 493, 510, 13, 51714, 51714, 509, 458, 411, 3440, 4150, 13, 51814, 51814], "temperature": 0.2, "avg_logprob": -0.5015249961663869, "compression_ratio": 2.0588235294117645, "no_speech_prob": 0.0032136384397745132}, {"id": 57, "seek": 25200, "start": 266.0, "end": 268.0, "text": " I would have been here when I was young.", "tokens": [50364, 286, 1143, 281, 352, 493, 293, 286, 1143, 281, 411, 4435, 456, 13, 50614, 50614, 663, 311, 309, 13, 50664, 50664, 509, 645, 257, 587, 11, 558, 30, 50714, 50714, 509, 576, 362, 668, 510, 562, 291, 645, 2037, 13, 50814, 50814, 1079, 11, 286, 576, 362, 668, 510, 13, 50914, 50914, 286, 576, 362, 668, 510, 562, 286, 390, 2037, 13, 51014, 51014, 286, 576, 362, 668, 510, 13, 51064, 51064, 286, 576, 362, 668, 510, 562, 286, 390, 2037, 13, 51164, 51164, 440, 1472, 295, 264, 6499, 390, 4418, 4494, 264, 8481, 11, 51464, 51464, 2577, 4963, 8475, 293, 20719, 264, 3676, 490, 4194, 493, 510, 13, 51714, 51714, 509, 458, 411, 3440, 4150, 13, 51814, 51814], "temperature": 0.2, "avg_logprob": -0.5015249961663869, "compression_ratio": 2.0588235294117645, "no_speech_prob": 0.0032136384397745132}, {"id": 58, "seek": 25200, "start": 268.0, "end": 274.0, "text": " The rest of the afternoon was spent walking the streets,", "tokens": [50364, 286, 1143, 281, 352, 493, 293, 286, 1143, 281, 411, 4435, 456, 13, 50614, 50614, 663, 311, 309, 13, 50664, 50664, 509, 645, 257, 587, 11, 558, 30, 50714, 50714, 509, 576, 362, 668, 510, 562, 291, 645, 2037, 13, 50814, 50814, 1079, 11, 286, 576, 362, 668, 510, 13, 50914, 50914, 286, 576, 362, 668, 510, 562, 286, 390, 2037, 13, 51014, 51014, 286, 576, 362, 668, 510, 13, 51064, 51064, 286, 576, 362, 668, 510, 562, 286, 390, 2037, 13, 51164, 51164, 440, 1472, 295, 264, 6499, 390, 4418, 4494, 264, 8481, 11, 51464, 51464, 2577, 4963, 8475, 293, 20719, 264, 3676, 490, 4194, 493, 510, 13, 51714, 51714, 509, 458, 411, 3440, 4150, 13, 51814, 51814], "temperature": 0.2, "avg_logprob": -0.5015249961663869, "compression_ratio": 2.0588235294117645, "no_speech_prob": 0.0032136384397745132}, {"id": 59, "seek": 25200, "start": 274.0, "end": 279.0, "text": " seeing familiar faces and remembering the stories from growing up here.", "tokens": [50364, 286, 1143, 281, 352, 493, 293, 286, 1143, 281, 411, 4435, 456, 13, 50614, 50614, 663, 311, 309, 13, 50664, 50664, 509, 645, 257, 587, 11, 558, 30, 50714, 50714, 509, 576, 362, 668, 510, 562, 291, 645, 2037, 13, 50814, 50814, 1079, 11, 286, 576, 362, 668, 510, 13, 50914, 50914, 286, 576, 362, 668, 510, 562, 286, 390, 2037, 13, 51014, 51014, 286, 576, 362, 668, 510, 13, 51064, 51064, 286, 576, 362, 668, 510, 562, 286, 390, 2037, 13, 51164, 51164, 440, 1472, 295, 264, 6499, 390, 4418, 4494, 264, 8481, 11, 51464, 51464, 2577, 4963, 8475, 293, 20719, 264, 3676, 490, 4194, 493, 510, 13, 51714, 51714, 509, 458, 411, 3440, 4150, 13, 51814, 51814], "temperature": 0.2, "avg_logprob": -0.5015249961663869, "compression_ratio": 2.0588235294117645, "no_speech_prob": 0.0032136384397745132}, {"id": 60, "seek": 25200, "start": 279.0, "end": 281.0, "text": " You know like meeting players.", "tokens": [50364, 286, 1143, 281, 352, 493, 293, 286, 1143, 281, 411, 4435, 456, 13, 50614, 50614, 663, 311, 309, 13, 50664, 50664, 509, 645, 257, 587, 11, 558, 30, 50714, 50714, 509, 576, 362, 668, 510, 562, 291, 645, 2037, 13, 50814, 50814, 1079, 11, 286, 576, 362, 668, 510, 13, 50914, 50914, 286, 576, 362, 668, 510, 562, 286, 390, 2037, 13, 51014, 51014, 286, 576, 362, 668, 510, 13, 51064, 51064, 286, 576, 362, 668, 510, 562, 286, 390, 2037, 13, 51164, 51164, 440, 1472, 295, 264, 6499, 390, 4418, 4494, 264, 8481, 11, 51464, 51464, 2577, 4963, 8475, 293, 20719, 264, 3676, 490, 4194, 493, 510, 13, 51714, 51714, 509, 458, 411, 3440, 4150, 13, 51814, 51814], "temperature": 0.2, "avg_logprob": -0.5015249961663869, "compression_ratio": 2.0588235294117645, "no_speech_prob": 0.0032136384397745132}, {"id": 61, "seek": 28100, "start": 281.0, "end": 286.0, "text": " You know like in the evening you get ready and then you come here all the young people come here.", "tokens": [50364, 509, 458, 411, 294, 264, 5634, 291, 483, 1919, 293, 550, 291, 808, 510, 439, 264, 2037, 561, 808, 510, 13, 50614, 50614, 286, 1194, 264, 5193, 307, 257, 938, 6148, 13, 50714, 50714, 3802, 1826, 309, 311, 5272, 13, 50864, 50864, 639, 390, 452, 14754, 311, 1159, 3945, 13, 51014, 51014, 467, 390, 264, 1159, 3945, 689, 452, 3546, 3264, 1203, 415, 3255, 965, 13, 51314, 51664], "temperature": 0.0, "avg_logprob": -0.32081808362688335, "compression_ratio": 1.5454545454545454, "no_speech_prob": 0.0007573461625725031}, {"id": 62, "seek": 28100, "start": 286.0, "end": 288.0, "text": " I thought the opening is a long dinner.", "tokens": [50364, 509, 458, 411, 294, 264, 5634, 291, 483, 1919, 293, 550, 291, 808, 510, 439, 264, 2037, 561, 808, 510, 13, 50614, 50614, 286, 1194, 264, 5193, 307, 257, 938, 6148, 13, 50714, 50714, 3802, 1826, 309, 311, 5272, 13, 50864, 50864, 639, 390, 452, 14754, 311, 1159, 3945, 13, 51014, 51014, 467, 390, 264, 1159, 3945, 689, 452, 3546, 3264, 1203, 415, 3255, 965, 13, 51314, 51664], "temperature": 0.0, "avg_logprob": -0.32081808362688335, "compression_ratio": 1.5454545454545454, "no_speech_prob": 0.0007573461625725031}, {"id": 63, "seek": 28100, "start": 288.0, "end": 291.0, "text": " Wait until it's Christmas.", "tokens": [50364, 509, 458, 411, 294, 264, 5634, 291, 483, 1919, 293, 550, 291, 808, 510, 439, 264, 2037, 561, 808, 510, 13, 50614, 50614, 286, 1194, 264, 5193, 307, 257, 938, 6148, 13, 50714, 50714, 3802, 1826, 309, 311, 5272, 13, 50864, 50864, 639, 390, 452, 14754, 311, 1159, 3945, 13, 51014, 51014, 467, 390, 264, 1159, 3945, 689, 452, 3546, 3264, 1203, 415, 3255, 965, 13, 51314, 51664], "temperature": 0.0, "avg_logprob": -0.32081808362688335, "compression_ratio": 1.5454545454545454, "no_speech_prob": 0.0007573461625725031}, {"id": 64, "seek": 28100, "start": 291.0, "end": 294.0, "text": " This was my grandfather's watch shop.", "tokens": [50364, 509, 458, 411, 294, 264, 5634, 291, 483, 1919, 293, 550, 291, 808, 510, 439, 264, 2037, 561, 808, 510, 13, 50614, 50614, 286, 1194, 264, 5193, 307, 257, 938, 6148, 13, 50714, 50714, 3802, 1826, 309, 311, 5272, 13, 50864, 50864, 639, 390, 452, 14754, 311, 1159, 3945, 13, 51014, 51014, 467, 390, 264, 1159, 3945, 689, 452, 3546, 3264, 1203, 415, 3255, 965, 13, 51314, 51664], "temperature": 0.0, "avg_logprob": -0.32081808362688335, "compression_ratio": 1.5454545454545454, "no_speech_prob": 0.0007573461625725031}, {"id": 65, "seek": 28100, "start": 294.0, "end": 300.0, "text": " It was the watch shop where my dad learned everything he knows today.", "tokens": [50364, 509, 458, 411, 294, 264, 5634, 291, 483, 1919, 293, 550, 291, 808, 510, 439, 264, 2037, 561, 808, 510, 13, 50614, 50614, 286, 1194, 264, 5193, 307, 257, 938, 6148, 13, 50714, 50714, 3802, 1826, 309, 311, 5272, 13, 50864, 50864, 639, 390, 452, 14754, 311, 1159, 3945, 13, 51014, 51014, 467, 390, 264, 1159, 3945, 689, 452, 3546, 3264, 1203, 415, 3255, 965, 13, 51314, 51664], "temperature": 0.0, "avg_logprob": -0.32081808362688335, "compression_ratio": 1.5454545454545454, "no_speech_prob": 0.0007573461625725031}, {"id": 66, "seek": 30000, "start": 300.0, "end": 310.0, "text": " More familiar faces and more catching up.", "tokens": [50364, 5048, 4963, 8475, 293, 544, 16124, 493, 13, 50864, 51664, 1018, 264, 786, 1437, 322, 264, 15697, 16300, 1314, 13, 51814, 51814], "temperature": 0.0, "avg_logprob": -0.1828455924987793, "compression_ratio": 1.0987654320987654, "no_speech_prob": 0.0008277648012153804}, {"id": 67, "seek": 30000, "start": 326.0, "end": 329.0, "text": " As the day went on the uncertainty washed away.", "tokens": [50364, 5048, 4963, 8475, 293, 544, 16124, 493, 13, 50864, 51664, 1018, 264, 786, 1437, 322, 264, 15697, 16300, 1314, 13, 51814, 51814], "temperature": 0.0, "avg_logprob": -0.1828455924987793, "compression_ratio": 1.0987654320987654, "no_speech_prob": 0.0008277648012153804}, {"id": 68, "seek": 32900, "start": 329.0, "end": 331.0, "text": " This was home.", "tokens": [50364, 639, 390, 1280, 13, 50464, 50464, 1981, 366, 527, 10669, 293, 294, 472, 636, 420, 264, 661, 321, 439, 2762, 4582, 13, 50714, 51014, 316, 587, 393, 1621, 294, 867, 3190, 293, 294, 867, 8078, 13, 51264, 51264, 583, 415, 787, 575, 472, 1280, 13, 51464], "temperature": 0.0, "avg_logprob": -0.13075865308443704, "compression_ratio": 1.3529411764705883, "no_speech_prob": 0.00024580603349022567}, {"id": 69, "seek": 32900, "start": 331.0, "end": 336.0, "text": " These are our roots and in one way or the other we all felt connected.", "tokens": [50364, 639, 390, 1280, 13, 50464, 50464, 1981, 366, 527, 10669, 293, 294, 472, 636, 420, 264, 661, 321, 439, 2762, 4582, 13, 50714, 51014, 316, 587, 393, 1621, 294, 867, 3190, 293, 294, 867, 8078, 13, 51264, 51264, 583, 415, 787, 575, 472, 1280, 13, 51464], "temperature": 0.0, "avg_logprob": -0.13075865308443704, "compression_ratio": 1.3529411764705883, "no_speech_prob": 0.00024580603349022567}, {"id": 70, "seek": 32900, "start": 342.0, "end": 347.0, "text": " A man can live in many places and in many houses.", "tokens": [50364, 639, 390, 1280, 13, 50464, 50464, 1981, 366, 527, 10669, 293, 294, 472, 636, 420, 264, 661, 321, 439, 2762, 4582, 13, 50714, 51014, 316, 587, 393, 1621, 294, 867, 3190, 293, 294, 867, 8078, 13, 51264, 51264, 583, 415, 787, 575, 472, 1280, 13, 51464], "temperature": 0.0, "avg_logprob": -0.13075865308443704, "compression_ratio": 1.3529411764705883, "no_speech_prob": 0.00024580603349022567}, {"id": 71, "seek": 34700, "start": 347.0, "end": 360.0, "text": " But he only has one home.", "tokens": [50364, 583, 415, 787, 575, 472, 1280, 13, 51014], "temperature": 0.0, "avg_logprob": -0.191293466091156, "compression_ratio": 0.8064516129032258, "no_speech_prob": 0.0001066101249307394}], "language": "en"}