{"0": {"Name": "The business of filming your daily life (ur mom ashley interview)", "Link": "https://youtube.com/watch?v=xp2VGAjHZWY"}, "1": {"Name": "How Dream Hacked YouTube (and broke the internet)", "Link": "https://youtube.com/watch?v=3QZkjsMfj3I"}, "2": {"Name": "How Hasan Minhaj escaped the YouTube Algorithm", "Link": "https://youtube.com/watch?v=NphQGsm4rvk"}, "3": {"Name": "We Toured Rhett and Link's Wildly Efficient Studio", "Link": "https://youtube.com/watch?v=cbBxEmGOfk4"}, "4": {"Name": "1 Million Subscribers", "Link": "https://youtube.com/watch?v=lBCOOTyU46M"}, "5": {"Name": "Why Jarvis Johnson Analyzes The Internet", "Link": "https://youtube.com/watch?v=OE4ti4alRN8"}, "6": {"Name": "How Rhett & Link Failed their way to YouTube's most successful show", "Link": "https://youtube.com/watch?v=w4iUuroktxw"}, "7": {"Name": "How Cody Ko & Noel Miller Turned a Joke into a Multi-Million Dollar Business", "Link": "https://youtube.com/watch?v=yNLqaQ6slkw"}, "8": {"Name": "The Nearly Impossible Job of Managing MrBeast", "Link": "https://youtube.com/watch?v=N5YW4JB07-8"}, "9": {"Name": "YouTubers ask us tough questions", "Link": "https://youtube.com/watch?v=gGBCbswZbnI"}, "10": {"Name": "TommyInnit on his Biggest Failures, YouTube Secrets, and friendship with Dream", "Link": "https://youtube.com/watch?v=0bC1ah_x8zo"}, "11": {"Name": "How KSI became an unlikely superstar", "Link": "https://youtube.com/watch?v=hYaGD0V2OkE"}, "12": {"Name": "How Ryan Trahan changed YouTube with $0.01", "Link": "https://youtube.com/watch?v=wkDlfvTed1c"}, "13": {"Name": "Why Michelle Khare is the Most Badass Human on YouTube", "Link": "https://youtube.com/watch?v=7qoe2qhcZ-Y"}, "14": {"Name": "How YouTube's Worst Inventor Built a Successful Product Design Company", "Link": "https://youtube.com/watch?v=88067BiKU4Y"}, "15": {"Name": "How ZHC Gained 13 Million Subscribers In A Year", "Link": "https://youtube.com/watch?v=jzMsnNxzejI"}, "16": {"Name": "Why he's the only honest man left in News.", "Link": "https://youtube.com/watch?v=iq71Cb2jEIE"}, "17": {"Name": "The Most Popular Kids in New York", "Link": "https://youtube.com/watch?v=pvtMJFPyiLM"}, "18": {"Name": "A Very Honest Conversation with Yes Theory", "Link": "https://youtube.com/watch?v=3vbZvRHpM8w"}, "19": {"Name": "YouTuber Merch: Winners and Losers pt. 4", "Link": "https://youtube.com/watch?v=7hrSj5qkHv4"}, "20": {"Name": "The Untold Story of Binging with Babish", "Link": "https://youtube.com/watch?v=VbNIh88Nq5k"}, "21": {"Name": "Why Emma Chamberlain Quit YouTube, Again.", "Link": "https://youtube.com/watch?v=XuVR_elE1Pw"}, "22": {"Name": "Van Neistat's Wildly Hand-Made Studio", "Link": "https://youtube.com/watch?v=r8bzWKBvZsE"}, "23": {"Name": "Can true art survive on YouTube?", "Link": "https://youtube.com/watch?v=9CxaZWkwHzE"}, "24": {"Name": "Why Drake wants to be on Chicken Shop Date (not Hot Ones)", "Link": "https://youtube.com/watch?v=x5lBJE2Ok8E"}, "25": {"Name": "How Ludwig Became The Biggest Twitch Streamer\u2026Then Left For Youtube", "Link": "https://youtube.com/watch?v=z_czmz_bJqk"}, "26": {"Name": "What you missed in Kanye's \"Jeen-Yuhs\"", "Link": "https://youtube.com/watch?v=irIN7SHvLDc"}, "27": {"Name": "Why Wordle Won't Go Away", "Link": "https://youtube.com/watch?v=t69cK3Ih_Og"}, "28": {"Name": "How Andrew Schulz took over YouTube", "Link": "https://youtube.com/watch?v=BB2HTaXTy0k"}, "29": {"Name": "How TikTok took down the Super Bowl", "Link": "https://youtube.com/watch?v=HmrjOq8epsg"}, "30": {"Name": "Why Ryan's World is the Richest kid on YouTube", "Link": "https://youtube.com/watch?v=MLyEDp7e0Q8"}, "31": {"Name": "Why Liza Koshy Disappeared", "Link": "https://youtube.com/watch?v=9cn_r1z6zjo"}, "32": {"Name": "How MrBeast could make even MORE money", "Link": "https://youtube.com/watch?v=o8UBXsiiS24"}, "33": {"Name": "Logan Paul and KSI: an unlikely love story", "Link": "https://youtube.com/watch?v=SpdWaOngRWM"}, "34": {"Name": "Inside MKBHD's $1,000,000 Studio", "Link": "https://youtube.com/watch?v=jz_qFyTrS8w"}, "35": {"Name": "Why MKBHD will be the oldest YouTuber ever", "Link": "https://youtube.com/watch?v=Dh909TbYn7Y"}, "36": {"Name": "The Story of Jeff Wittek", "Link": "https://youtube.com/watch?v=G5c6qof96DM"}, "37": {"Name": "Why Lilly Singh Left YouTube (and then came back)", "Link": "https://youtube.com/watch?v=UZSwDZ72Lp8"}, "38": {"Name": "How MrBeast \u201cStole\u201d Squid Game", "Link": "https://youtube.com/watch?v=dbOXYhjpXAc"}, "39": {"Name": "YouTuber Merch: Winners and Losers pt. 3", "Link": "https://youtube.com/watch?v=YVuIm8OLz-8"}, "40": {"Name": "The Metaverse has problems", "Link": "https://youtube.com/watch?v=r-Y1LRtsFaU"}, "41": {"Name": "Dude Perfect's YouTube Struggle", "Link": "https://youtube.com/watch?v=_TAxmgPQtzc"}, "42": {"Name": "Billion Dollar CEO talks about his biggest mistake", "Link": "https://youtube.com/watch?v=vwtRRdmZSYw"}, "43": {"Name": "The Story of Karl", "Link": "https://youtube.com/watch?v=xIC1nS4DU6M"}, "44": {"Name": "Life after burnout", "Link": "https://youtube.com/watch?v=PiGCHXt5eBs"}, "45": {"Name": "How Squid Game Revived Netflix and Took over the World.", "Link": "https://youtube.com/watch?v=6OICqRSTRjY"}, "46": {"Name": "The Silent Genius of Khaby Lame", "Link": "https://youtube.com/watch?v=71Xz6bYoRGc"}, "47": {"Name": "The Dark Side of the D'Amelios", "Link": "https://youtube.com/watch?v=7PIlp-FSN5I"}, "48": {"Name": "The Full Story of MrBeast", "Link": "https://youtube.com/watch?v=c8VcUnz3nVc"}, "49": {"Name": "How MrBeast spends $48,000,000 a year on videos", "Link": "https://youtube.com/watch?v=TW7cH2wLv00"}, "50": {"Name": "Dear Emma Chamberlain, You've Changed.", "Link": "https://youtube.com/watch?v=BVEzAyZXctY"}, "51": {"Name": "How Jake Paul broke the boxing industry", "Link": "https://youtube.com/watch?v=dwFBlFS4dus"}, "52": {"Name": "The Wildly Lucrative World of Ice Cream TikTok", "Link": "https://youtube.com/watch?v=p0Y82yGFqAw"}, "53": {"Name": "Why everyone leaves the Hype House", "Link": "https://youtube.com/watch?v=nxyThD3-GTw"}, "54": {"Name": "He sold his company to Amazon for $970,000,000 ft @Justin Kan\u200b", "Link": "https://youtube.com/watch?v=wUOdBXYIMM8"}, "55": {"Name": "How Tai Verdes Made It", "Link": "https://youtube.com/watch?v=pkiW9ygtddA"}, "56": {"Name": "The Full Story of Victoria Paris", "Link": "https://youtube.com/watch?v=O0C417mFrRQ"}, "57": {"Name": "Alex Cooper's $60,000,000 Deal with Spotify", "Link": "https://youtube.com/watch?v=ZlR0Rsu_VeU"}, "58": {"Name": "How college athletes went from $0 to $1 million overnight", "Link": "https://youtube.com/watch?v=TAFYbWgX8K0"}, "59": {"Name": "The High Price of Airrack's Success", "Link": "https://youtube.com/watch?v=rcHNOkA9NNk"}, "60": {"Name": "How Much Money Airrack Makes (1.6M Subscribers)", "Link": "https://youtube.com/watch?v=lQyAdgLwbLk"}, "61": {"Name": "The Disney-fication of the Nelk Boys", "Link": "https://youtube.com/watch?v=HGhT5GMhf8A"}, "62": {"Name": "Why Indians Are Taking Over YouTube", "Link": "https://youtube.com/watch?v=WVI2GUdJp2Y"}, "63": {"Name": "Who Really Won Logan Paul vs Floyd Mayweather?", "Link": "https://youtube.com/watch?v=9w0kTRvOQWA"}, "64": {"Name": "Roblox, Explained (for Beginners)", "Link": "https://youtube.com/watch?v=j7eETkQcHLA"}, "65": {"Name": "Bo Burnham's Complicated Relationship with Himself", "Link": "https://youtube.com/watch?v=5EfQqwDmOnI"}, "66": {"Name": "Why Ryan Trahan is the Next MrBeast", "Link": "https://youtube.com/watch?v=7eWpg3WyelA"}, "67": {"Name": "Is Addison Rae Making Real Music?", "Link": "https://youtube.com/watch?v=lBGq8vWx7B0"}, "68": {"Name": "Jeff Wittek's $2.4 Million Dollar Mistake", "Link": "https://youtube.com/watch?v=lGmrpX7KkcU"}, "69": {"Name": "Influencers are over. ft @Shelby Church", "Link": "https://youtube.com/watch?v=pVhrApLIraI"}, "70": {"Name": "Every Way We Make Money", "Link": "https://youtube.com/watch?v=f5WZgw0WGto"}, "71": {"Name": "How Dixie D'Amelio Murdered Late Night", "Link": "https://youtube.com/watch?v=Fz27v1gnCFM"}, "72": {"Name": "How We Sold an NFT for $___", "Link": "https://youtube.com/watch?v=BSXMM9Y1blk"}, "73": {"Name": "How Much YouTube Paid Us Since The Beginning (14M Views)", "Link": "https://youtube.com/watch?v=TBx1uYdq5nk"}, "74": {"Name": "Why Emma Chamberlain is the New Casey Neistat", "Link": "https://youtube.com/watch?v=Xy0cKyWL2J8"}, "75": {"Name": "Why Nas Daily Left A $120,000 Job at Venmo to Make Videos (ft @Nas Daily)", "Link": "https://youtube.com/watch?v=6R4zxswb8gQ"}, "76": {"Name": "The Problem with Buying Stock in Logan Paul (BitClout)", "Link": "https://youtube.com/watch?v=knl2UOFr8bk"}, "77": {"Name": "How MrBeast Spends More Money Than He Makes", "Link": "https://youtube.com/watch?v=jaKINKK09FY"}, "78": {"Name": "How Lil Nas X sold his soul to break the internet", "Link": "https://youtube.com/watch?v=mwhbGLiDC3Q"}, "79": {"Name": "Meet the girls saving social media", "Link": "https://youtube.com/watch?v=N3BA2RBRBT4"}, "80": {"Name": "David Dobrik: A Lesson for Creators", "Link": "https://youtube.com/watch?v=wZrGJM7dGvY"}, "81": {"Name": "Charli D\u2019Amelio is selling out (of cold brew)", "Link": "https://youtube.com/watch?v=Sxh6Kai4tyI"}, "82": {"Name": "How this NFT sold for $69 Million (Beeple)", "Link": "https://youtube.com/watch?v=Ptk6P7Lc6rs"}, "83": {"Name": "The Full Story of MKBHD", "Link": "https://youtube.com/watch?v=pWH1TF1ZfKA"}, "84": {"Name": "How Logan Paul Made Millions Selling Air (NFT's)", "Link": "https://youtube.com/watch?v=Qg9hKz-AjIA"}, "85": {"Name": "YouTuber Merch: Winners and Losers pt. 2", "Link": "https://youtube.com/watch?v=9HsnKZnREgM"}, "86": {"Name": "How Much Money YouTube Paid Us in 2020", "Link": "https://youtube.com/watch?v=g--OcS0WyHQ"}, "87": {"Name": "Surprising Our First Subscribers with Gifts", "Link": "https://youtube.com/watch?v=C6pngdRHaiI"}, "88": {"Name": "The Story of Coolman Coffeedan", "Link": "https://youtube.com/watch?v=ZQrqhfe8kGE"}, "89": {"Name": "Creator of the Year Goes to...", "Link": "https://youtube.com/watch?v=9ZaetFop0AA"}, "90": {"Name": "How it started, How it's going", "Link": "https://youtube.com/watch?v=g5Ojh12HIrw"}, "91": {"Name": "How to make better YouTube Thumbnails", "Link": "https://youtube.com/watch?v=GPX4PiwQz0U"}, "92": {"Name": "Making Merch that actually sells ft Amanda Rach Lee", "Link": "https://youtube.com/watch?v=tSU8GEt2Ylg"}, "93": {"Name": "When To Quit Your Job ft Jake Roper (Vsauce3)", "Link": "https://youtube.com/watch?v=Nfqo3cGmrJ4"}, "94": {"Name": "YouTuber Merch: Winners and Losers pt. 1", "Link": "https://youtube.com/watch?v=fyt-E1A-jwc"}, "95": {"Name": "We quit YouTube.", "Link": "https://youtube.com/watch?v=1WQbMVhIMEY"}, "96": {"Name": "How Watching YouTube Changes You.", "Link": "https://youtube.com/watch?v=5Xh8fAflpQY"}, "97": {"Name": "Our $20,000 YouTube Studio Transformation", "Link": "https://youtube.com/watch?v=q-7x6jaTA-0"}, "98": {"Name": "$200,000 Education VS $200 Education", "Link": "https://youtube.com/watch?v=ePAu90YVYMY"}, "99": {"Name": "The best (and worst) election ads of 2020", "Link": "https://youtube.com/watch?v=y1QSLcAwiK0"}, "100": {"Name": "How Airrack Grew 0 to 1 Million Subscribers and Risked Everything", "Link": "https://youtube.com/watch?v=hPM7DDuzjZY"}, "101": {"Name": "The Future of Phones", "Link": "https://youtube.com/watch?v=q3oKPfPtT2Q"}, "102": {"Name": "We Stayed in a $7 Million Dollar Vacation Home", "Link": "https://youtube.com/watch?v=QzNOBP7IiDY"}, "103": {"Name": "We bought Cardi B's OnlyFans so you don't have to", "Link": "https://youtube.com/watch?v=jNGUBzKadtw"}, "104": {"Name": "Why David Dobrik Gives Away Teslas", "Link": "https://youtube.com/watch?v=IMqiE_b5uPo"}, "105": {"Name": "The TikTok Ban, Explained", "Link": "https://youtube.com/watch?v=9JrPkteJVS4"}, "106": {"Name": "How Much Money YouTube Pays Us (125k Subscribers)", "Link": "https://youtube.com/watch?v=lAMFzDc2zLE"}, "107": {"Name": "Why MrBeast will be YouTube's first Billionaire", "Link": "https://youtube.com/watch?v=oopD9FX7a_c"}, "108": {"Name": "How much money can you make on TikTok?", "Link": "https://youtube.com/watch?v=r-LAw78weAQ"}, "109": {"Name": "TikTok's Takeover, Explained.", "Link": "https://youtube.com/watch?v=lh17G4AClKk"}, "110": {"Name": "The Disappearance of David Dobrik", "Link": "https://youtube.com/watch?v=6zoPS4SFhIc"}, "111": {"Name": "Why Video Games are the Future of Concerts", "Link": "https://youtube.com/watch?v=_MWqGYX78WE"}, "112": {"Name": "24 Hrs in Quarantine", "Link": "https://youtube.com/watch?v=Bbt3HCz1b24"}, "113": {"Name": "$560,000 Dollar Air Jordans, Explained", "Link": "https://youtube.com/watch?v=Exm5p-vCjMs"}, "114": {"Name": "John Krasinski's Some Good News, Honest Thoughts", "Link": "https://youtube.com/watch?v=viFznUG5_bU"}, "115": {"Name": "A Tiger King Analysis Video", "Link": "https://youtube.com/watch?v=uFDjvPZPig4"}, "116": {"Name": "Is this The End of Late Night?", "Link": "https://youtube.com/watch?v=XF2LLhd5jxg"}, "117": {"Name": "How Minimalism Became Mainstream", "Link": "https://youtube.com/watch?v=G7Yu6_3epOk"}, "118": {"Name": "Our Perspective on The New Normal", "Link": "https://youtube.com/watch?v=WbZLhLCU5Ec"}, "119": {"Name": "Why \"Dude with Sign\" is the Best Account on Instagram.", "Link": "https://youtube.com/watch?v=fVtQKC2NK84"}, "120": {"Name": "Our Secret Project with Samsung", "Link": "https://youtube.com/watch?v=PDZ6sYal5A0"}, "121": {"Name": "Why Hot Ones is the Best Show on the Internet", "Link": "https://youtube.com/watch?v=wLMNMGgJ_a0"}, "122": {"Name": "Why David Dobrik Loves Science So Much", "Link": "https://youtube.com/watch?v=b7tBOJ7Hyl4"}, "123": {"Name": "Why Emma Chamberlain Drinks So Much Coffee", "Link": "https://youtube.com/watch?v=WFe68voApTI"}, "124": {"Name": "Logan Paul KSI 2, Explained.", "Link": "https://youtube.com/watch?v=6ZygdEyYpiE"}, "125": {"Name": "The Curious Case of Lil Miquela", "Link": "https://youtube.com/watch?v=i4rwlQ7IA1U"}, "126": {"Name": "Why does Cam Newton have a YouTube Channel?", "Link": "https://youtube.com/watch?v=VaEXDJL8dfE"}, "127": {"Name": "Why Indians are taking over Hollywood", "Link": "https://youtube.com/watch?v=vXgBYT9T7iM"}, "128": {"Name": "Apple's Complex Relationship with Memes", "Link": "https://youtube.com/watch?v=i05bI03nzv4"}, "129": {"Name": "Why David Dobrik Laughs So Much", "Link": "https://youtube.com/watch?v=fjZSLHvkg14"}, "130": {"Name": "Finding the Solution to Traffic", "Link": "https://youtube.com/watch?v=TnyUCA-4BuQ"}, "131": {"Name": "Why MrBeast is the next PewDiePie", "Link": "https://youtube.com/watch?v=c5mAdStj52c"}, "132": {"Name": "Why YouTubers are charging for content now.", "Link": "https://youtube.com/watch?v=upYpZgh0tIU"}, "133": {"Name": "Why YouTube won't talk about this Indian rapper.", "Link": "https://youtube.com/watch?v=0T_HyckDSfA"}, "134": {"Name": "The Power of Lil Nas X and Logan Paul", "Link": "https://youtube.com/watch?v=UkY8BIVEbx8"}, "135": {"Name": "F*ck it, let's just get jobs.", "Link": "https://youtube.com/watch?v=7y1zfAPz2Rk"}, "136": {"Name": "Hey, we're back \ud83d\udc4b\ud83c\udffc\ud83d\udc4b\ud83c\udffe", "Link": "https://youtube.com/watch?v=xSTGLbguHYY"}, "137": {"Name": "How to Fix INSTAGRAM", "Link": "https://youtube.com/watch?v=sNGOgBcCcA4"}, "138": {"Name": "NOT a Samsung Galaxy Fold Review", "Link": "https://youtube.com/watch?v=re_osGoZf9w"}, "139": {"Name": "Why NBC Chose a YouTuber for Late Night", "Link": "https://youtube.com/watch?v=j0JP6sL6sqA"}, "140": {"Name": "Chasing my childhood dream of becoming a Rockstar", "Link": "https://youtube.com/watch?v=Bsm9a10hVbo"}, "141": {"Name": "Yes Theory gave us ONE WEEK to make a MOVIE", "Link": "https://youtube.com/watch?v=enbVsRjRBSY"}, "142": {"Name": "My Lowest Moment as an Entrepreneur", "Link": "https://youtube.com/watch?v=m9YlMWwlgHQ"}, "143": {"Name": "The Story of Colin and Samir", "Link": "https://youtube.com/watch?v=Yk4KG9Vc2Hs"}, "144": {"Name": "Surprising Yes Theory with a Gift", "Link": "https://youtube.com/watch?v=zp9OCb3-mdQ"}, "145": {"Name": "Why we left BuzzFeed", "Link": "https://youtube.com/watch?v=Q1qmiTya2rc"}, "146": {"Name": "Hey it's been a while \ud83d\udc4b\ud83c\udffc\ud83d\udc4b\ud83c\udffe", "Link": "https://youtube.com/watch?v=cX-Y-xtmVTI"}, "147": {"Name": "Stop Hating on Tik Tok Cringe", "Link": "https://youtube.com/watch?v=l_Naty_LoK4"}, "148": {"Name": "Trying the Best Burgers in Los Angeles", "Link": "https://youtube.com/watch?v=2RoG7Mhu5UI"}, "149": {"Name": "Why Politicians don't use YouTube", "Link": "https://youtube.com/watch?v=1YTwwAj0Pcw"}, "150": {"Name": "WTF is a VPN?", "Link": "https://youtube.com/watch?v=CI4weml_WWY"}, "151": {"Name": "Shane Dawson changed everything.", "Link": "https://youtube.com/watch?v=SsQfHVetJdA"}, "152": {"Name": "What is Will Smith doing to YouTube?", "Link": "https://youtube.com/watch?v=OxsqnYbisB0"}, "153": {"Name": "YouTube is Changing: Article 13 Explained", "Link": "https://youtube.com/watch?v=EM-No65BGcc"}, "154": {"Name": "What We Do Here", "Link": "https://youtube.com/watch?v=MqWVh1PYGt4"}, "155": {"Name": "What's Wrong with Apple?", "Link": "https://youtube.com/watch?v=cro1sY1GT78"}, "156": {"Name": "Day in the Life of Colin and Samir feat. Yes Theory", "Link": "https://youtube.com/watch?v=OXwKGWDvHfk"}, "157": {"Name": "Not Your Average PewDiePie vs T-Series Video", "Link": "https://youtube.com/watch?v=x6-nKRHXUS0"}, "158": {"Name": "Dear Casey Neistat Wanabees", "Link": "https://youtube.com/watch?v=Rk5OEuBQgOM"}, "159": {"Name": "The Effect of Moment Lenses", "Link": "https://youtube.com/watch?v=oSbFXT9Y-7g"}, "160": {"Name": "I Didn't Go to Film School", "Link": "https://youtube.com/watch?v=jx554F3BPKk"}, "161": {"Name": "New Yorker Tries LA's Best Pizza", "Link": "https://youtube.com/watch?v=0T4KT_vHX3Q"}, "162": {"Name": "What Happens When you Turn 30", "Link": "https://youtube.com/watch?v=XicLniORQgo"}, "163": {"Name": "Who is Cody Wanner?", "Link": "https://youtube.com/watch?v=vSfIMsnINsg"}, "164": {"Name": "Lil Miquela Robots are taking over Social Media", "Link": "https://youtube.com/watch?v=K-hnbTqo6ko"}, "165": {"Name": "How to Conquer Your Fears: A Skydiving Story", "Link": "https://youtube.com/watch?v=WoznWa7QTN4"}, "166": {"Name": "Searching for a Great Documentary Story", "Link": "https://youtube.com/watch?v=CBwQtl72k2A"}, "167": {"Name": "Reacting to Instagram TV (IGTV)", "Link": "https://youtube.com/watch?v=sCWdaLe2qJU"}, "168": {"Name": "A Week in the Life of Colin and Samir", "Link": "https://youtube.com/watch?v=pwkOf7A6hkw"}, "169": {"Name": "The Making of a Viral Book", "Link": "https://youtube.com/watch?v=_DRsu5Cv3O0"}, "170": {"Name": "Where We've Been", "Link": "https://youtube.com/watch?v=mOX0WpHZL0A"}, "171": {"Name": "How to Grow an Audience", "Link": "https://youtube.com/watch?v=vqp-87KaqTA"}, "172": {"Name": "Why Trick Shots STILL Break the Internet", "Link": "https://youtube.com/watch?v=e1rEmRRcOXA"}, "173": {"Name": "Why does every YouTuber have a podcast?", "Link": "https://youtube.com/watch?v=SuclRePmrso"}, "174": {"Name": "Colin and Samir's Filmmaking Everyday Carry", "Link": "https://youtube.com/watch?v=1D0wFMjVRQU"}, "175": {"Name": "Colin and Samir's 5 Rules of Filmmaking (on the internet)", "Link": "https://youtube.com/watch?v=nL8375jedtI"}, "176": {"Name": "How a Blind YouTuber Makes Videos", "Link": "https://youtube.com/watch?v=71Dl3eKi78E"}, "177": {"Name": "A little more about us", "Link": "https://youtube.com/watch?v=rhx_VXSaSHQ"}, "178": {"Name": "24 Hours in Utah", "Link": "https://youtube.com/watch?v=zEXlzhjLkgY"}, "179": {"Name": "Answering Subscriber Questions on the Street", "Link": "https://youtube.com/watch?v=KNaqN8FfN3g"}, "180": {"Name": "Life Through Our Lenses", "Link": "https://youtube.com/watch?v=zGQYGXXOo1A"}, "181": {"Name": "Behind the Scenes with Mango Street", "Link": "https://youtube.com/watch?v=mY-ocubOA4Q"}, "182": {"Name": "Twitch vs YouTube ft. Sam Sheffer and Justin Odisho", "Link": "https://youtube.com/watch?v=20SF0ypIWF0"}, "183": {"Name": "A Crash Course in Twitch", "Link": "https://youtube.com/watch?v=acthJViewHY"}, "184": {"Name": "They Invited Us to Dinner (YES THEORY)", "Link": "https://youtube.com/watch?v=N3fmmRmlEQs"}, "185": {"Name": "Putting yourself on camera (VLOG)", "Link": "https://youtube.com/watch?v=o6IluoEuLdU"}, "186": {"Name": "Your most IMPORTANT video", "Link": "https://youtube.com/watch?v=x5z6kZ8Ms3A"}, "187": {"Name": "A Goal of Ours", "Link": "https://youtube.com/watch?v=Fe4k7zYow_8"}, "188": {"Name": "$16 Coffee: Is it Worth it???", "Link": "https://youtube.com/watch?v=rnd0dtbduZU"}, "189": {"Name": "How to Get 50,000 Subscribers", "Link": "https://youtube.com/watch?v=x_XHWAQvV90"}, "190": {"Name": "KICK DOWN THE DOOR", "Link": "https://youtube.com/watch?v=HmSOib-jRHc"}, "191": {"Name": "How Collabs Happen: Mary Spender", "Link": "https://youtube.com/watch?v=2wVfZXL7wWQ"}, "192": {"Name": "How Should YouTube Communicate?", "Link": "https://youtube.com/watch?v=uuqnJNQ_FlM"}, "193": {"Name": "Jack Coyne's ONE tip for YouTubers...wait til the end", "Link": "https://youtube.com/watch?v=oemgPLZKVFI"}, "194": {"Name": "Jack Coyne Is Trending", "Link": "https://youtube.com/watch?v=CTtZZgyikC8"}, "195": {"Name": "100,000 Subscribers in 3 DAYS", "Link": "https://youtube.com/watch?v=pckdId5VMUI"}, "196": {"Name": "What Happened to our Beme Show?", "Link": "https://youtube.com/watch?v=kIaMxe-Jdqk"}, "197": {"Name": "Why does Will Smith have a YouTube channel?", "Link": "https://youtube.com/watch?v=eGGWnRhJr-E"}, "198": {"Name": "24 Hours to Meet YES THEORY", "Link": "https://youtube.com/watch?v=VCBngh5dOgI"}, "199": {"Name": "Censorship on YouTube: A Solution", "Link": "https://youtube.com/watch?v=Ua643jRnUqE"}, "200": {"Name": "Rylo 360 Camera Unboxing and Test", "Link": "https://youtube.com/watch?v=vRE91dh0xXw"}, "201": {"Name": "4 Reasons YouTube will DOMINATE in 2018", "Link": "https://youtube.com/watch?v=qOmDq0nvmmk"}, "202": {"Name": "Mic Comparison: Shure SM7B vs Rode NT1A", "Link": "https://youtube.com/watch?v=x9I5lAit11k"}, "203": {"Name": "Beme News: A Comprehensive Review", "Link": "https://youtube.com/watch?v=eK1RvkTz93g"}, "204": {"Name": "iPhone X vs  iPhone 8 Explained", "Link": "https://youtube.com/watch?v=mB0qIXMJyIs"}, "205": {"Name": "Colin's 6000 mile surprise", "Link": "https://youtube.com/watch?v=w-2ZgVedG_0"}, "206": {"Name": "First Haircut in 4 Years", "Link": "https://youtube.com/watch?v=li7uDQsi1OI"}, "207": {"Name": "Skateboarding in Death Valley | Now Boarding ep 3", "Link": "https://youtube.com/watch?v=5clRjfNiHoA"}, "208": {"Name": "World's Shortest Train Route", "Link": "https://youtube.com/watch?v=wTKe3P1TzVY"}, "209": {"Name": "How to be Productive", "Link": "https://youtube.com/watch?v=JORfxyg93uQ"}, "210": {"Name": "Is this too much?", "Link": "https://youtube.com/watch?v=rZc4suHh21U"}, "211": {"Name": "Our vlog camera", "Link": "https://youtube.com/watch?v=d1Qh9-ok4UI"}, "212": {"Name": "The Perfect Skateboard Box | NOW BOARDING ep 2", "Link": "https://youtube.com/watch?v=HH-5zS4E6ts"}, "213": {"Name": "Starting a Cruiser Skateboard Company | NOW BOARDING ep 1", "Link": "https://youtube.com/watch?v=cL7YDBOZaPY"}, "214": {"Name": "Felix Gray Glasses Unboxing", "Link": "https://youtube.com/watch?v=pE-FNprmPPM"}, "215": {"Name": "Paul Rabil Bones Shirt Collab", "Link": "https://youtube.com/watch?v=D5PZn8YdKxM"}, "216": {"Name": "CLEANING UP OUR STUDIO", "Link": "https://youtube.com/watch?v=38gzcYHoxqM"}, "217": {"Name": "LA FREEWAYS FROM ABOVE", "Link": "https://youtube.com/watch?v=dsAT1NI0S0Q"}, "218": {"Name": "BEST VLOG CAMERA YOU CAN'T BUY", "Link": "https://youtube.com/watch?v=50EvFY019JA"}, "219": {"Name": "Branding a Building", "Link": "https://youtube.com/watch?v=p_7_dtI0QKc"}, "220": {"Name": "About Our Skateboards", "Link": "https://youtube.com/watch?v=JrXghzDFnD0"}, "221": {"Name": "Letter from Mumbai", "Link": "https://youtube.com/watch?v=A-x3ILbGo9w"}, "222": {"Name": "Friends at the Studio", "Link": "https://youtube.com/watch?v=Kkp0Fedru-w"}, "223": {"Name": "How I got my start in graphic design", "Link": "https://youtube.com/watch?v=H_9cm7ELIM4"}, "224": {"Name": "How to Start Filmmaking: An Exercise", "Link": "https://youtube.com/watch?v=ZHbCG26me6I"}, "225": {"Name": "Should you go to film school?", "Link": "https://youtube.com/watch?v=5MnoAsJ1Idg"}, "226": {"Name": "Unboxing Our New Stickers", "Link": "https://youtube.com/watch?v=KdzTs2w-p2A"}, "227": {"Name": "San Diego Travel Vlog Day 2", "Link": "https://youtube.com/watch?v=Wxnv13wGZAg"}, "228": {"Name": "Should we get this camera? Sony a5100", "Link": "https://youtube.com/watch?v=Y8v-jea5Gi0"}, "229": {"Name": "Helicopter Flight Over New York City", "Link": "https://youtube.com/watch?v=zPVZcvgB1P4"}, "230": {"Name": "A DAY IN THE LIFE OF COLIN", "Link": "https://youtube.com/watch?v=9tv5clYvqOk"}, "231": {"Name": "A DAY IN THE LIFE OF SAMIR", "Link": "https://youtube.com/watch?v=hpJ_umfsdpA"}, "232": {"Name": "Big in Japan", "Link": "https://youtube.com/watch?v=8nDV8snjSGY"}, "233": {"Name": "We Took Over Casey Neistat's Vlog", "Link": "https://youtube.com/watch?v=NI5oVNeA2cw"}, "234": {"Name": "Los Angeles Drone Flight", "Link": "https://youtube.com/watch?v=fkJk_g9wag0"}, "235": {"Name": "Snapchat Spectacles Review", "Link": "https://youtube.com/watch?v=fqLVb0Gb9G4"}, "236": {"Name": "Spending A Year Homeless | Old Man SAXON", "Link": "https://youtube.com/watch?v=1VwwLH5FCKs"}, "237": {"Name": "How to Quit Your Job and Travel", "Link": "https://youtube.com/watch?v=QW8CW6CXo54"}, "238": {"Name": "Send Us A Story", "Link": "https://youtube.com/watch?v=F29rbezLL94"}, "239": {"Name": "Home Away from Home", "Link": "https://youtube.com/watch?v=qt2xEQxcYsg"}, "240": {"Name": "Home to India", "Link": "https://youtube.com/watch?v=Up5aADUVagU"}, "241": {"Name": "November 8th, 2016", "Link": "https://youtube.com/watch?v=xcaSBHB9dbE"}, "242": {"Name": "State of the Channel | November 3rd, 2016", "Link": "https://youtube.com/watch?v=pLsQVs5l87Y"}, "243": {"Name": "Our Favorite Place in Los Angeles", "Link": "https://youtube.com/watch?v=YUx-PavD7EA"}, "244": {"Name": "A DAY IN THE LIFE OF COLIN AND SAMIR", "Link": "https://youtube.com/watch?v=KRIpc_oN_zQ"}, "245": {"Name": "Portland Travel Guide", "Link": "https://youtube.com/watch?v=34LNfDnaNDw"}, "246": {"Name": "How to Launch a Startup", "Link": "https://youtube.com/watch?v=Igr_QCVGR-0"}, "247": {"Name": "This is Fairfax: Streetwear + Community", "Link": "https://youtube.com/watch?v=-HV9VRPIoag"}}